{
  "piid": "N0002419C2115",
  "label": "BPMI Columbia Class Industrial Base Increase",
  "vendor": "BPMI",
  "gid": "CONT_AWD_N0002419C2115_9700_-NONE-_-NONE-",
  "group": "contracts",
  "prime_recipient": "BECHTEL PLANT MACHINERY, INC.",
  "prime_amount": 3004573964.0,
  "subaward_count": 67,
  "subaward_total": 527960368.0,
  "subawards": [
    {
      "id": 2449856,
      "subaward_number": "S86000",
      "description": "HEAVY EQUIPMENT",
      "action_date": "2019-03-29",
      "amount": 271890053.0,
      "recipient_name": "BWXT NUCLEAR OPERATIONS GROUP, INC."
    },
    {
      "id": 1427798,
      "subaward_number": "VARIOUS",
      "description": "HEAVY EQUIPMENT",
      "action_date": "2019-12-31",
      "amount": 46776320.0,
      "recipient_name": "BWX TECHNOLOGIES, INC."
    },
    {
      "id": 1431069,
      "subaward_number": "VARIOUS",
      "description": "PUMPS",
      "action_date": "2019-03-29",
      "amount": 31044787.0,
      "recipient_name": "CURTISS-WRIGHT ELECTRO-MECHANICAL CORPORATION"
    },
    {
      "id": 2458497,
      "subaward_number": "G300074",
      "description": "INSTRUMENTATION",
      "action_date": "2019-11-29",
      "amount": 28830745.0,
      "recipient_name": "DRS NAVAL POWER SYSTEMS INC"
    },
    {
      "id": 2460187,
      "subaward_number": "G300366",
      "description": "INSTRUMENTATON",
      "action_date": "2021-01-29",
      "amount": 19158234.0,
      "recipient_name": "DRS NAVAL POWER SYSTEMS INC"
    },
    {
      "id": 2458883,
      "subaward_number": "S300439",
      "description": "PIPE AND FITTINGS",
      "action_date": "2021-03-31",
      "amount": 13748393.0,
      "recipient_name": "TAYLOR FORGE ENGINEERED SYSTEMS, INC."
    },
    {
      "id": 1415682,
      "subaward_number": "VARIOUS",
      "description": "VALVES",
      "action_date": "2019-01-31",
      "amount": 13597998.0,
      "recipient_name": "CURTISS-WRIGHT FLOW CONTROL CORPORATION"
    },
    {
      "id": 2457387,
      "subaward_number": "G200579",
      "description": "INSTRUMENTATION",
      "action_date": "2021-03-31",
      "amount": 10608587.0,
      "recipient_name": "POWER PARAGON INC"
    },
    {
      "id": 1421423,
      "subaward_number": "G200627",
      "description": "INSTRUMENTATION",
      "action_date": "2019-05-30",
      "amount": 9446025.0,
      "recipient_name": "L3HARRIS MARITIME POWER & ENERGY SOLUTIONS, INC."
    },
    {
      "id": 2453970,
      "subaward_number": "VARIOUS",
      "description": "INSTRUMENTATION",
      "action_date": "2019-01-31",
      "amount": 8951680.0,
      "recipient_name": "LOCKHEED MARTIN CORP"
    },
    {
      "id": 1427429,
      "subaward_number": "VARIOUS",
      "description": "INSTRUMENTATION",
      "action_date": "2019-01-31",
      "amount": 8951680.0,
      "recipient_name": "PEERLESS INSTRUMENT CO., INC."
    },
    {
      "id": 2459304,
      "subaward_number": "S200673",
      "description": "FORGINGS",
      "action_date": "2019-04-30",
      "amount": 7307301.0,
      "recipient_name": "TAYLOR FORGE ENGINEERED SYSTEMS, INC."
    },
    {
      "id": 1433267,
      "subaward_number": "C200437",
      "description": "VALVES",
      "action_date": "2019-03-29",
      "amount": 6158643.0,
      "recipient_name": "HAMILL MANUFACTURING COMPANY"
    },
    {
      "id": 2459046,
      "subaward_number": "C300412",
      "description": "PUMPS",
      "action_date": "2021-03-31",
      "amount": 6126989.0,
      "recipient_name": "DC FABRICATORS INC"
    },
    {
      "id": 1434566,
      "subaward_number": "C300433",
      "description": "PUMPS",
      "action_date": "2021-03-31",
      "amount": 5138442.0,
      "recipient_name": "CURTISS-WRIGHT ELECTRO-MECHANICAL CORPORATION"
    },
    {
      "id": 2452226,
      "subaward_number": "C300004",
      "description": "HEAVY EQUIPMENT",
      "action_date": "2021-02-26",
      "amount": 3840018.0,
      "recipient_name": "GRAHAM CORP"
    },
    {
      "id": 1426509,
      "subaward_number": "VARIOUS",
      "description": "VALVES",
      "action_date": "2021-03-31",
      "amount": 3144157.0,
      "recipient_name": "HAMILL MANUFACTURING COMPANY"
    },
    {
      "id": 2456646,
      "subaward_number": "VARIOUS",
      "description": "INSTRUMENTATION",
      "action_date": "2019-03-29",
      "amount": 3098729.0,
      "recipient_name": "DRS NAVAL POWER SYSTEMS INC"
    },
    {
      "id": 2458945,
      "subaward_number": "S300250",
      "description": "HEAVY EQUIPMENT",
      "action_date": "2021-02-26",
      "amount": 2925644.0,
      "recipient_name": "BWX TECHNOLOGIES, INC."
    },
    {
      "id": 1426492,
      "subaward_number": "VARIOUS",
      "description": "INSTRUMENTATION",
      "action_date": "2021-03-31",
      "amount": 2756060.0,
      "recipient_name": "PEERLESS INSTRUMENT CO., INC."
    },
    {
      "id": 1427254,
      "subaward_number": "C200525",
      "description": "PUMPS",
      "action_date": "2019-04-30",
      "amount": 2423495.0,
      "recipient_name": "CURTISS-WRIGHT ELECTRO-MECHANICAL CORPORATION"
    },
    {
      "id": 2459550,
      "subaward_number": "VARIOUS",
      "description": "INSTRUMENTATION",
      "action_date": "2019-01-31",
      "amount": 2029239.0,
      "recipient_name": "DRS NAVAL POWER SYSTEMS INC"
    },
    {
      "id": 2452451,
      "subaward_number": "VARIOUS",
      "description": "INSTRUMENTATION",
      "action_date": "2021-03-31",
      "amount": 1571219.0,
      "recipient_name": "LOCKHEED MARTIN CORP"
    },
    {
      "id": 2456000,
      "subaward_number": "VARIOUS",
      "description": "VALVES",
      "action_date": "2019-03-29",
      "amount": 1562815.0,
      "recipient_name": "VACCO INDUSTRIES"
    },
    {
      "id": 2457493,
      "subaward_number": "G200750",
      "description": "INSTRUMENTATION",
      "action_date": "2019-02-28",
      "amount": 1550585.0,
      "recipient_name": "DRS NAVAL POWER SYSTEMS INC"
    },
    {
      "id": 1430082,
      "subaward_number": "C113117",
      "description": "PUMPS",
      "action_date": "2019-07-31",
      "amount": 1503944.0,
      "recipient_name": "CURTISS-WRIGHT ELECTRO-MECHANICAL CORPORATION"
    },
    {
      "id": 2456890,
      "subaward_number": "C200497",
      "description": "PLANT EQUIPMENT",
      "action_date": "2019-01-31",
      "amount": 1233438.0,
      "recipient_name": "PRECISION CUSTOM COMPONENTS, LLC"
    },
    {
      "id": 1426108,
      "subaward_number": "S86000",
      "description": "HEAVY EQUIPMENT",
      "action_date": "2019-08-30",
      "amount": 1189372.0,
      "recipient_name": "BWX TECHNOLOGIES, INC."
    },
    {
      "id": 2454147,
      "subaward_number": "C300767",
      "description": "VALVES",
      "action_date": "2021-02-26",
      "amount": 890488.0,
      "recipient_name": "VACCO INDUSTRIES"
    },
    {
      "id": 1427326,
      "subaward_number": "G200851",
      "description": "INSTRUMENTATION",
      "action_date": "2019-05-30",
      "amount": 849087.0,
      "recipient_name": "PEERLESS INSTRUMENT CO., INC."
    },
    {
      "id": 2457001,
      "subaward_number": "C300657",
      "description": "INSTRUMENTATION",
      "action_date": "2021-03-31",
      "amount": 801393.0,
      "recipient_name": "DRS NAVAL POWER SYSTEMS INC"
    },
    {
      "id": 1431958,
      "subaward_number": "S86000",
      "description": "HEAVY EQUIPMENT",
      "action_date": "2019-06-28",
      "amount": 748571.0,
      "recipient_name": "BWX TECHNOLOGIES, INC."
    },
    {
      "id": 1428719,
      "subaward_number": "VARIOUS",
      "description": "INSTRUMENTATION",
      "action_date": "2021-01-29",
      "amount": 688123.0,
      "recipient_name": "PEERLESS INSTRUMENT CO., INC."
    },
    {
      "id": 1429790,
      "subaward_number": "S86000",
      "description": "HEAVY EQUIPMENT",
      "action_date": "2019-11-29",
      "amount": 604322.0,
      "recipient_name": "BWX TECHNOLOGIES, INC."
    },
    {
      "id": 1425806,
      "subaward_number": "C117161",
      "description": "PUMPS",
      "action_date": "2019-01-31",
      "amount": 549234.0,
      "recipient_name": "CURTISS-WRIGHT ELECTRO-MECHANICAL CORPORATION"
    },
    {
      "id": 1430452,
      "subaward_number": "C300348",
      "description": "VALVES",
      "action_date": "2021-02-26",
      "amount": 538827.0,
      "recipient_name": "HAMILL MANUFACTURING COMPANY"
    },
    {
      "id": 2452675,
      "subaward_number": "G200748",
      "description": "INSTRUMENTATION",
      "action_date": "2019-02-28",
      "amount": 522436.0,
      "recipient_name": "MIRION TECHNOLOGIES (IST) CORPORATION"
    },
    {
      "id": 1416795,
      "subaward_number": "S300863",
      "description": "INSTRUMENTATION",
      "action_date": "2021-03-31",
      "amount": 516510.0,
      "recipient_name": "CONNECTRONICS CORP"
    },
    {
      "id": 1423299,
      "subaward_number": "S200720",
      "description": "CABLING",
      "action_date": "2019-05-31",
      "amount": 498508.0,
      "recipient_name": "CONNECTRONICS CORP"
    },
    {
      "id": 2459626,
      "subaward_number": "S86000",
      "description": "HEAVY EQUIPMENT",
      "action_date": "2021-03-31",
      "amount": 417571.0,
      "recipient_name": "BWX TECHNOLOGIES, INC."
    },
    {
      "id": 1429839,
      "subaward_number": "C200437",
      "description": "VALVES",
      "action_date": "2019-12-31",
      "amount": 294554.0,
      "recipient_name": "HAMILL MANUFACTURING COMPANY"
    },
    {
      "id": 1417273,
      "subaward_number": "K300224",
      "description": "VALVES",
      "action_date": "2019-11-29",
      "amount": 291866.0,
      "recipient_name": "GENERAL NUCLEAR CORP"
    },
    {
      "id": 1424592,
      "subaward_number": "VARIOUS",
      "description": "VALVES",
      "action_date": "2021-03-31",
      "amount": 248093.0,
      "recipient_name": "GENERAL NUCLEAR CORP"
    },
    {
      "id": 1430627,
      "subaward_number": "VARIOUS",
      "description": "INSTRUMENTATION",
      "action_date": "2019-02-28",
      "amount": 246797.0,
      "recipient_name": "PEERLESS INSTRUMENT CO., INC."
    },
    {
      "id": 2459106,
      "subaward_number": "G300569",
      "description": "INSTRUMENTATION",
      "action_date": "2021-02-26",
      "amount": 219249.0,
      "recipient_name": "DRS NAVAL POWER SYSTEMS INC"
    },
    {
      "id": 1433006,
      "subaward_number": "C200481",
      "description": "PUMPS",
      "action_date": "2021-03-31",
      "amount": 203409.0,
      "recipient_name": "CURTISS-WRIGHT ELECTRO-MECHANICAL CORPORATION"
    },
    {
      "id": 1430964,
      "subaward_number": "C113137",
      "description": "PUMPS",
      "action_date": "2019-06-28",
      "amount": 193246.0,
      "recipient_name": "CURTISS-WRIGHT ELECTRO-MECHANICAL CORPORATION"
    },
    {
      "id": 2456805,
      "subaward_number": "G115909",
      "description": "INSTRUMENTATION",
      "action_date": "2019-08-30",
      "amount": 186380.0,
      "recipient_name": "POWER PARAGON INC"
    },
    {
      "id": 1430638,
      "subaward_number": "C113117",
      "description": "PUMPS",
      "action_date": "2021-01-29",
      "amount": 175696.0,
      "recipient_name": "CURTISS-WRIGHT ELECTRO-MECHANICAL CORPORATION"
    },
    {
      "id": 1426328,
      "subaward_number": "C113117",
      "description": "PUMPS",
      "action_date": "2019-11-29",
      "amount": 172381.0,
      "recipient_name": "CURTISS-WRIGHT ELECTRO-MECHANICAL CORPORATION"
    },
    {
      "id": 1415925,
      "subaward_number": "C200484",
      "description": "VALVES",
      "action_date": "2019-02-28",
      "amount": 144928.0,
      "recipient_name": "GENERAL NUCLEAR CORP"
    },
    {
      "id": 1423912,
      "subaward_number": "S85000",
      "description": "HEAVY EQUIPMENT",
      "action_date": "2019-01-31",
      "amount": 142597.0,
      "recipient_name": "BWXT NUCLEAR OPERATIONS GROUP, INC."
    },
    {
      "id": 2458311,
      "subaward_number": "G200579",
      "description": "INSTRUMENTATION",
      "action_date": "2019-12-31",
      "amount": 125215.0,
      "recipient_name": "POWER PARAGON INC"
    },
    {
      "id": 1417712,
      "subaward_number": "C200559",
      "description": "VALVES",
      "action_date": "2019-01-31",
      "amount": 124496.0,
      "recipient_name": "GENERAL NUCLEAR CORP"
    },
    {
      "id": 2457085,
      "subaward_number": "G200579",
      "description": "INSTRUMENTATION",
      "action_date": "2019-11-29",
      "amount": 122503.0,
      "recipient_name": "POWER PARAGON INC"
    },
    {
      "id": 2457268,
      "subaward_number": "C201136",
      "description": "PLANT EQUIPMENT",
      "action_date": "2019-06-28",
      "amount": 112248.0,
      "recipient_name": "PENN STATE TOOL & DIE CORP"
    },
    {
      "id": 1421122,
      "subaward_number": "C300728",
      "description": "VALVES",
      "action_date": "2021-01-29",
      "amount": 111712.0,
      "recipient_name": "GENERAL NUCLEAR CORP"
    },
    {
      "id": 2459793,
      "subaward_number": "G155909",
      "description": "INSTRUMENTATION",
      "action_date": "2019-06-28",
      "amount": 105932.0,
      "recipient_name": "POWER PARAGON INC"
    },
    {
      "id": 2457247,
      "subaward_number": "G200961",
      "description": "INSTRUMENTATION",
      "action_date": "2019-04-30",
      "amount": 101650.0,
      "recipient_name": "DRS NAVAL POWER SYSTEMS INC"
    },
    {
      "id": 2456581,
      "subaward_number": "G115909",
      "description": "INSTRUMENTATION",
      "action_date": "2019-03-29",
      "amount": 99112.0,
      "recipient_name": "POWER PARAGON INC"
    },
    {
      "id": 2459709,
      "subaward_number": "G115909",
      "description": "INSTRUMENTATION",
      "action_date": "2019-07-31",
      "amount": 87000.0,
      "recipient_name": "POWER PARAGON INC"
    },
    {
      "id": 1426320,
      "subaward_number": "C113117",
      "description": "PUMPS",
      "action_date": "2019-05-30",
      "amount": 62908.0,
      "recipient_name": "CURTISS-WRIGHT ELECTRO-MECHANICAL CORPORATION"
    },
    {
      "id": 1422043,
      "subaward_number": "G300872",
      "description": "INSTRUMENTATION",
      "action_date": "2021-01-29",
      "amount": 60330.0,
      "recipient_name": "GOVERNMENT SECURE SOLUTIONS CGI INC."
    },
    {
      "id": 2458338,
      "subaward_number": "G200579",
      "description": "INSTRUMENTATION",
      "action_date": "2019-10-31",
      "amount": 37739.0,
      "recipient_name": "POWER PARAGON INC"
    },
    {
      "id": 2453926,
      "subaward_number": "G300156",
      "description": "INSTRUMENTATION",
      "action_date": "2021-01-29",
      "amount": 36195.0,
      "recipient_name": "LOCKHEED MARTIN CORP"
    },
    {
      "id": 2459575,
      "subaward_number": "G115909",
      "description": "INSTRUMENTATION",
      "action_date": "2019-04-30",
      "amount": 33339.0,
      "recipient_name": "POWER PARAGON INC"
    },
    {
      "id": 2459976,
      "subaward_number": "G115909",
      "description": "INSTRUMENTATION",
      "action_date": "2019-01-31",
      "amount": 31131.0,
      "recipient_name": "POWER PARAGON INC"
    }
  ]
}