{
  "award_id": "CONT_AWD_N0010419PNE62_9700_-NONE-_-NONE-",
  "count": 2,
  "results": [
    {
      "id": "CONT_TX_9700_-NONE-_N0010419PNE62_0_-NONE-_0",
      "type": "B",
      "type_description": "PURCHASE ORDER",
      "action_date": "2019-09-17",
      "action_type": null,
      "action_type_description": null,
      "modification_number": "0",
      "description": "SHAFT,TRANSMISSION; NSN: 7HH 4320 014369747; REF NO: 12324F18; REQUIREMENT = REPAIR.",
      "federal_action_obligation": 20000.0,
      "face_value_loan_guarantee": 0.0,
      "original_loan_subsidy_cost": 0.0
    },
    {
      "id": "CONT_TX_9700_-NONE-_N0010419PNE62_P00001_-NONE-_0",
      "type": "B",
      "type_description": "PURCHASE ORDER",
      "action_date": "2019-11-25",
      "action_type": "B",
      "action_type_description": "SUPPLEMENTAL AGREEMENT FOR WORK WITHIN SCOPE",
      "modification_number": "P00001",
      "description": "SHAFT TRANSMISSION NSN: 7HH 4320 014369747 PART #: 12324F18 REQUIREMENT  BER.",
      "federal_action_obligation": -11000.0,
      "face_value_loan_guarantee": 0.0,
      "original_loan_subsidy_cost": 0.0
    }
  ]
}