{
  "piid": "N0002422C4485",
  "label": "BAE-Guns/VLS: CODE 440A CNO EXECUTION CONTRACTS\nUSS MUSTIN DDG 89 FY22 DMP \nBILATERAL EXTENSION MODIFICATION TO SETTLE\nRCCS 290G CLIN/",
  "vendor": "BAE SYSTEMS SAN DIEGO SHIP REPAIR INC.",
  "gid": "CONT_AWD_N0002422C4485_9700_-NONE-_-NONE-",
  "group": "contracts",
  "prime_recipient": "BAE SYSTEMS MARITIME SOLUTIONS SAN DIEGO INC.",
  "prime_amount": 114651057.1,
  "subaward_count": 273,
  "subaward_total": 8197296.099999996,
  "subawards": [
    {
      "id": 1868934,
      "subaward_number": "52P401690-0",
      "description": "DIRECT SUBCONTRACT COSTS",
      "action_date": "2022-04-26",
      "amount": 890530.0,
      "recipient_name": "OCKERMAN AUTOMATION CONSULTING INC"
    },
    {
      "id": 59157,
      "subaward_number": "52P403011-1",
      "description": "DIRECT SUBCONTRACT COSTS",
      "action_date": "2023-01-04",
      "amount": 849196.0,
      "recipient_name": "RIX INDUSTRIES"
    },
    {
      "id": 1869928,
      "subaward_number": "52P402737-8",
      "description": "DIRECT SUBCONTRACT COSTS",
      "action_date": "2023-01-24",
      "amount": 697217.0,
      "recipient_name": "AMP UNITED LLC"
    },
    {
      "id": 9576915,
      "subaward_number": "52P402358-0",
      "description": "DIRECT SUBCONTRACT COSTS",
      "action_date": "2022-05-17",
      "amount": 295007.0,
      "recipient_name": "ROLLS-ROYCE MARINE NORTH AMERICA INC."
    },
    {
      "id": 65115,
      "subaward_number": "52P403728-0",
      "description": "DIRECT MATERIAL EXPENSE",
      "action_date": "2022-07-22",
      "amount": 250687.0,
      "recipient_name": "ALFA LAVAL INC"
    },
    {
      "id": 64077,
      "subaward_number": "52P403728-1",
      "description": "DIRECT MATERIAL EXPENSE",
      "action_date": "2023-04-19",
      "amount": 199323.55,
      "recipient_name": "ALFA LAVAL INC"
    },
    {
      "id": 1870511,
      "subaward_number": "52P402249-7",
      "description": "DIRECT SUBCONTRACT COSTS",
      "action_date": "2023-05-22",
      "amount": 168160.0,
      "recipient_name": "L3HARRIS MARITIME SERVICES INC"
    },
    {
      "id": 1870438,
      "subaward_number": "52P402249-9",
      "description": "DIRECT SUBCONTRACT COSTS",
      "action_date": "2023-05-25",
      "amount": 168160.0,
      "recipient_name": "L3HARRIS MARITIME SERVICES INC"
    },
    {
      "id": 46087,
      "subaward_number": "52P402933-15",
      "description": "DIRECT SUBCONTRACT COSTS",
      "action_date": "2023-01-23",
      "amount": 167520.0,
      "recipient_name": "PREMIER SCAFFOLD, INC."
    },
    {
      "id": 45596,
      "subaward_number": "52P402933-7",
      "description": "DIRECT SUBCONTRACT COSTS",
      "action_date": "2022-12-08",
      "amount": 146000.0,
      "recipient_name": "PREMIER SCAFFOLD, INC."
    },
    {
      "id": 1866557,
      "subaward_number": "52P406210-0",
      "description": "DIRECT MATERIAL EXPENSE",
      "action_date": "2022-12-16",
      "amount": 118782.0,
      "recipient_name": "PAR MARINE SERVICES LLC"
    },
    {
      "id": 48709,
      "subaward_number": "52P406380-0",
      "description": "DIRECT MATERIAL EXPENSE",
      "action_date": "2023-01-04",
      "amount": 107978.0,
      "recipient_name": "DURAMAX MARINE, LLC"
    },
    {
      "id": 54135,
      "subaward_number": "52P402346-36",
      "description": "DIRECT SUBCONTRACT COSTS",
      "action_date": "2023-11-20",
      "amount": 106863.25,
      "recipient_name": "SOUTH BAY SAND BLASTING AND TANK CLEANING, INC."
    },
    {
      "id": 1863833,
      "subaward_number": "52P401436-0",
      "description": "DIRECT MATERIAL EXPENSE",
      "action_date": "2022-04-15",
      "amount": 106330.0,
      "recipient_name": "CORNELL-CARR CO., INC."
    },
    {
      "id": 53092,
      "subaward_number": "52P403199-2",
      "description": "DIRECT SUBCONTRACT COSTS",
      "action_date": "2022-12-01",
      "amount": 98010.0,
      "recipient_name": "IN-PLACE MACHINING COMPANY, LLC"
    },
    {
      "id": 1868990,
      "subaward_number": "52P403742-0",
      "description": "DIRECT MATERIAL EXPENSE",
      "action_date": "2022-07-22",
      "amount": 96768.0,
      "recipient_name": "ALCO INVESTMENT COMPANY"
    },
    {
      "id": 57919,
      "subaward_number": "52P401530-0",
      "description": "DIRECT MATERIAL EXPENSE",
      "action_date": "2022-04-19",
      "amount": 94000.0,
      "recipient_name": "PORTABLE STORAGE OF SAN DIEGO, INC."
    },
    {
      "id": 56509,
      "subaward_number": "52P402986-7",
      "description": "DIRECT SUBCONTRACT COSTS",
      "action_date": "2023-02-10",
      "amount": 86795.0,
      "recipient_name": "IMIA, LLC"
    },
    {
      "id": 57209,
      "subaward_number": "52P402346-2",
      "description": "DIRECT SUBCONTRACT COSTS",
      "action_date": "2022-09-01",
      "amount": 83522.0,
      "recipient_name": "SOUTH BAY SAND BLASTING AND TANK CLEANING, INC."
    },
    {
      "id": 1868831,
      "subaward_number": "52P402737-14",
      "description": "DIRECT SUBCONTRACT COSTS",
      "action_date": "2023-06-02",
      "amount": 82728.0,
      "recipient_name": "AMP UNITED LLC"
    },
    {
      "id": 48593,
      "subaward_number": "52P401532-0",
      "description": "DIRECT MATERIAL EXPENSE",
      "action_date": "2022-04-20",
      "amount": 82053.0,
      "recipient_name": "SEA SHIELD MARINE PRODUCTS, INC."
    },
    {
      "id": 64128,
      "subaward_number": "52P401783-0",
      "description": "DIRECT MATERIAL EXPENSE",
      "action_date": "2022-04-28",
      "amount": 81448.0,
      "recipient_name": "ASKEW INDUSTRIAL CORPORATION"
    },
    {
      "id": 61871,
      "subaward_number": "52P403248-8",
      "description": "DIRECT SUBCONTRACT COSTS",
      "action_date": "2023-01-13",
      "amount": 80784.0,
      "recipient_name": "L3HARRIS MARITIME SERVICES INC"
    },
    {
      "id": 1872144,
      "subaward_number": "52P406181-0",
      "description": "DIRECT MATERIAL EXPENSE",
      "action_date": "2022-12-16",
      "amount": 78851.0,
      "recipient_name": "CHARTER INDUSTRIAL SUPPLY, INC."
    },
    {
      "id": 1870124,
      "subaward_number": "52P406412-0",
      "description": "DIRECT MATERIAL EXPENSE",
      "action_date": "2023-01-05",
      "amount": 78375.0,
      "recipient_name": "GOODRICH CORPORATION"
    },
    {
      "id": 60881,
      "subaward_number": "52P402346-30",
      "description": "DIRECT SUBCONTRACT COSTS",
      "action_date": "2023-09-25",
      "amount": 75168.25,
      "recipient_name": "SOUTH BAY SAND BLASTING AND TANK CLEANING, INC."
    },
    {
      "id": 1869662,
      "subaward_number": "52P408624-2",
      "description": "DIRECT SUBCONTRACT COSTS",
      "action_date": "2023-11-20",
      "amount": 74659.2,
      "recipient_name": "BOB TURNER'S CRANE SERVICE INCORPORATED"
    },
    {
      "id": 53912,
      "subaward_number": "52P403527-0",
      "description": "DIRECT MATERIAL EXPENSE",
      "action_date": "2022-07-11",
      "amount": 74106.0,
      "recipient_name": "LISTER CHAIN & FORGE INC"
    },
    {
      "id": 1869467,
      "subaward_number": "52P401463-0",
      "description": "DIRECT MATERIAL EXPENSE",
      "action_date": "2022-04-15",
      "amount": 70299.0,
      "recipient_name": "ISOVOLTA INC."
    },
    {
      "id": 54896,
      "subaward_number": "52P401416-0",
      "description": "DIRECT MATERIAL EXPENSE",
      "action_date": "2022-04-13",
      "amount": 68650.0,
      "recipient_name": "SPEC-BUILT SYSTEMS, INC."
    },
    {
      "id": 59830,
      "subaward_number": "52P402346-39",
      "description": "DIRECT SUBCONTRACT COSTS",
      "action_date": "2023-12-12",
      "amount": 65585.55,
      "recipient_name": "SOUTH BAY SAND BLASTING AND TANK CLEANING, INC."
    },
    {
      "id": 1873212,
      "subaward_number": "52P401383-0",
      "description": "DIRECT MATERIAL EXPENSE",
      "action_date": "2022-04-11",
      "amount": 65425.0,
      "recipient_name": "PACIFIC MARITIME INDUSTRIES CORP."
    },
    {
      "id": 53357,
      "subaward_number": "52P403408-1",
      "description": "DIRECT FREIGHT EXPENSE",
      "action_date": "2022-12-13",
      "amount": 60266.0,
      "recipient_name": "HEVIQUIP LLC"
    },
    {
      "id": 44944,
      "subaward_number": "52P403092-5",
      "description": "DIRECT SUBCONTRACT COSTS",
      "action_date": "2023-12-11",
      "amount": 59000.0,
      "recipient_name": "PRIME TIME COATINGS  INC"
    },
    {
      "id": 58004,
      "subaward_number": "52P402346-11",
      "description": "DIRECT SUBCONTRACT COSTS",
      "action_date": "2023-03-17",
      "amount": 58888.0,
      "recipient_name": "SOUTH BAY SAND BLASTING AND TANK CLEANING, INC."
    },
    {
      "id": 54692,
      "subaward_number": "52P402346-10",
      "description": "DIRECT SUBCONTRACT COSTS",
      "action_date": "2023-03-17",
      "amount": 58888.0,
      "recipient_name": "SOUTH BAY SAND BLASTING AND TANK CLEANING, INC."
    },
    {
      "id": 50405,
      "subaward_number": "52P410371-0",
      "description": "DIRECT MATERIAL EXPENSE",
      "action_date": "2023-10-11",
      "amount": 58823.64,
      "recipient_name": "DEFENSE MARITIME SOLUTIONS, INC."
    },
    {
      "id": 46538,
      "subaward_number": "52P402933-36",
      "description": "DIRECT SUBCONTRACT COSTS",
      "action_date": "2023-09-14",
      "amount": 58130.0,
      "recipient_name": "PREMIER SCAFFOLD, INC."
    },
    {
      "id": 52658,
      "subaward_number": "52P405918-0",
      "description": "DIRECT MATERIAL EXPENSE",
      "action_date": "2022-12-02",
      "amount": 57105.0,
      "recipient_name": "ROLLS-ROYCE MARINE NORTH AMERICA INC."
    },
    {
      "id": 47330,
      "subaward_number": "52P405918-0",
      "description": "DIRECT MATERIAL EXPENSE",
      "action_date": "2023-01-06",
      "amount": 57105.0,
      "recipient_name": "ROLLS-ROYCE MARINE NORTH AMERICA INC."
    },
    {
      "id": 1871160,
      "subaward_number": "52P402249-12",
      "description": "DIRECT SUBCONTRACT COSTS",
      "action_date": "2023-10-12",
      "amount": 55455.0,
      "recipient_name": "L3HARRIS MARITIME SERVICES INC"
    },
    {
      "id": 58208,
      "subaward_number": "52P401454-0",
      "description": "DIRECT MATERIAL EXPENSE",
      "action_date": "2022-04-15",
      "amount": 53800.0,
      "recipient_name": "SPEC-BUILT SYSTEMS, INC."
    },
    {
      "id": 54254,
      "subaward_number": "52P402346-12",
      "description": "DIRECT SUBCONTRACT COSTS",
      "action_date": "2023-04-05",
      "amount": 51710.0,
      "recipient_name": "SOUTH BAY SAND BLASTING AND TANK CLEANING, INC."
    },
    {
      "id": 1870765,
      "subaward_number": "52P406544-0",
      "description": "OTHER DIRECT COSTS",
      "action_date": "2023-01-18",
      "amount": 50000.0,
      "recipient_name": "CLEAN HARBORS ENVIRONMENTAL SERVICES INC"
    },
    {
      "id": 1874746,
      "subaward_number": "52P406164-0",
      "description": "DIRECT MATERIAL EXPENSE",
      "action_date": "2022-12-15",
      "amount": 49591.0,
      "recipient_name": "CHARTER INDUSTRIAL SUPPLY, INC."
    },
    {
      "id": 1864628,
      "subaward_number": "52P403312-3",
      "description": "DIRECT EQUIPMENT RENTAL",
      "action_date": "2023-08-02",
      "amount": 48331.9,
      "recipient_name": "UNITED RENTALS NORTH AMERICA INC"
    },
    {
      "id": 1869690,
      "subaward_number": "52P408624-6",
      "description": "DIRECT SUBCONTRACT COSTS",
      "action_date": "2024-01-29",
      "amount": 48244.0,
      "recipient_name": "BOB TURNER'S CRANE SERVICE INCORPORATED"
    },
    {
      "id": 53067,
      "subaward_number": "52P402933-16",
      "description": "DIRECT SUBCONTRACT COSTS",
      "action_date": "2023-01-25",
      "amount": 47389.0,
      "recipient_name": "PREMIER SCAFFOLD, INC."
    },
    {
      "id": 60536,
      "subaward_number": "52P402986-6",
      "description": "DIRECT SUBCONTRACT COSTS",
      "action_date": "2023-02-06",
      "amount": 46777.0,
      "recipient_name": "IMIA, LLC"
    },
    {
      "id": 51218,
      "subaward_number": "52P402933-26",
      "description": "DIRECT SUBCONTRACT COSTS",
      "action_date": "2023-05-15",
      "amount": 45308.0,
      "recipient_name": "PREMIER SCAFFOLD, INC."
    },
    {
      "id": 61054,
      "subaward_number": "52P401608-0",
      "description": "DIRECT MATERIAL EXPENSE",
      "action_date": "2022-04-21",
      "amount": 45030.0,
      "recipient_name": "DOVER PUMPS & PROCESS SOLUTIONS SEGMENT INC"
    },
    {
      "id": 1874948,
      "subaward_number": "52P401667-0",
      "description": "DIRECT MATERIAL EXPENSE",
      "action_date": "2022-04-25",
      "amount": 43230.0,
      "recipient_name": "PACIFIC MARITIME INDUSTRIES CORP."
    },
    {
      "id": 52678,
      "subaward_number": "52P402933-30",
      "description": "DIRECT SUBCONTRACT COSTS",
      "action_date": "2023-06-30",
      "amount": 41130.0,
      "recipient_name": "PREMIER SCAFFOLD, INC."
    },
    {
      "id": 1865537,
      "subaward_number": "52P402669-1",
      "description": "DIRECT SUBCONTRACT COSTS",
      "action_date": "2023-01-11",
      "amount": 40823.0,
      "recipient_name": "PAR MARINE SERVICES LLC"
    },
    {
      "id": 1869998,
      "subaward_number": "52P401462-0",
      "description": "DIRECT MATERIAL EXPENSE",
      "action_date": "2022-04-15",
      "amount": 40017.0,
      "recipient_name": "ISOVOLTA INC."
    },
    {
      "id": 50895,
      "subaward_number": "52P403092-6",
      "description": "DIRECT SUBCONTRACT COSTS",
      "action_date": "2023-12-13",
      "amount": 39985.0,
      "recipient_name": "PRIME TIME COATINGS  INC"
    },
    {
      "id": 54179,
      "subaward_number": "52P402346-14",
      "description": "DIRECT SUBCONTRACT COSTS",
      "action_date": "2023-04-20",
      "amount": 39096.0,
      "recipient_name": "SOUTH BAY SAND BLASTING AND TANK CLEANING, INC."
    },
    {
      "id": 46080,
      "subaward_number": "52P402933-32",
      "description": "DIRECT SUBCONTRACT COSTS",
      "action_date": "2023-07-21",
      "amount": 38860.0,
      "recipient_name": "PREMIER SCAFFOLD, INC."
    },
    {
      "id": 53701,
      "subaward_number": "52P402346-38",
      "description": "DIRECT SUBCONTRACT COSTS",
      "action_date": "2023-12-06",
      "amount": 38492.0,
      "recipient_name": "SOUTH BAY SAND BLASTING AND TANK CLEANING, INC."
    },
    {
      "id": 56682,
      "subaward_number": "52P408662-0",
      "description": "DIRECT MATERIAL EXPENSE",
      "action_date": "2023-05-17",
      "amount": 38440.0,
      "recipient_name": "EVOQUA WATER TECHNOLOGIES LLC"
    },
    {
      "id": 46471,
      "subaward_number": "52P403092-3",
      "description": "DIRECT SUBCONTRACT COSTS",
      "action_date": "2023-09-25",
      "amount": 37285.0,
      "recipient_name": "PRIME TIME COATINGS  INC"
    },
    {
      "id": 51007,
      "subaward_number": "52P411296-0",
      "description": "DIRECT MATERIAL EXPENSE",
      "action_date": "2024-01-11",
      "amount": 36835.5,
      "recipient_name": "POTTER ELECTRIC, INC."
    },
    {
      "id": 55772,
      "subaward_number": "52P404390-0",
      "description": "DIRECT MATERIAL EXPENSE",
      "action_date": "2022-09-07",
      "amount": 36257.0,
      "recipient_name": "CALEDONIA PIPEWORK LLC"
    },
    {
      "id": 48336,
      "subaward_number": "52P403092-8",
      "description": "DIRECT SUBCONTRACT COSTS",
      "action_date": "2024-01-03",
      "amount": 36200.0,
      "recipient_name": "PRIME TIME COATINGS  INC"
    },
    {
      "id": 47038,
      "subaward_number": "52P402302-1",
      "description": "DIRECT EQUIPMENT RENTAL",
      "action_date": "2022-07-11",
      "amount": 35509.0,
      "recipient_name": "UNITED RENTALS (NORTH AMERICA), INC."
    },
    {
      "id": 1863920,
      "subaward_number": "52P402302-3",
      "description": "DIRECT EQUIPMENT RENTAL",
      "action_date": "2022-12-14",
      "amount": 34279.0,
      "recipient_name": "UNITED RENTALS (NORTH AMERICA), INC."
    },
    {
      "id": 1873939,
      "subaward_number": "52P405964-0",
      "description": "DIRECT MATERIAL EXPENSE",
      "action_date": "2022-12-06",
      "amount": 33983.0,
      "recipient_name": "CHARTER INDUSTRIAL SUPPLY, INC."
    },
    {
      "id": 49971,
      "subaward_number": "52P402616-7",
      "description": "DIRECT SUBCONTRACT COSTS",
      "action_date": "2023-10-16",
      "amount": 33701.0,
      "recipient_name": "DEFENSE MARITIME SOLUTIONS, INC."
    },
    {
      "id": 51907,
      "subaward_number": "52P402933-39",
      "description": "DIRECT SUBCONTRACT COSTS",
      "action_date": "2023-10-10",
      "amount": 33540.0,
      "recipient_name": "PREMIER SCAFFOLD, INC."
    },
    {
      "id": 1865885,
      "subaward_number": "52P403698-5",
      "description": "DIRECT SUBCONTRACT COSTS",
      "action_date": "2024-08-01",
      "amount": 33516.0,
      "recipient_name": "ALFA LAVAL INC"
    },
    {
      "id": 45457,
      "subaward_number": "52P402933-20",
      "description": "DIRECT SUBCONTRACT COSTS",
      "action_date": "2023-02-24",
      "amount": 33333.0,
      "recipient_name": "PREMIER SCAFFOLD, INC."
    },
    {
      "id": 65255,
      "subaward_number": "52P401657-0",
      "description": "DIRECT MATERIAL EXPENSE",
      "action_date": "2022-04-25",
      "amount": 33286.0,
      "recipient_name": "ASKEW INDUSTRIAL CORPORATION"
    },
    {
      "id": 1864132,
      "subaward_number": "52P401510-0",
      "description": "DIRECT MATERIAL EXPENSE",
      "action_date": "2022-04-19",
      "amount": 33058.0,
      "recipient_name": "ROLLS-ROYCE MARINE NORTH AMERICA INC."
    },
    {
      "id": 1875028,
      "subaward_number": "52P401726-0",
      "description": "DIRECT MATERIAL EXPENSE",
      "action_date": "2022-04-26",
      "amount": 32125.0,
      "recipient_name": "PACIFIC MARITIME INDUSTRIES CORP."
    },
    {
      "id": 45437,
      "subaward_number": "52P402933-34",
      "description": "DIRECT SUBCONTRACT COSTS",
      "action_date": "2023-08-15",
      "amount": 31760.0,
      "recipient_name": "PREMIER SCAFFOLD, INC."
    },
    {
      "id": 47025,
      "subaward_number": "52P409819-0",
      "description": "DIRECT MATERIAL EXPENSE",
      "action_date": "2023-08-17",
      "amount": 31453.39,
      "recipient_name": "ALFA LAVAL INC"
    },
    {
      "id": 51960,
      "subaward_number": "52P402933-42",
      "description": "DIRECT SUBCONTRACT COSTS",
      "action_date": "2023-11-28",
      "amount": 31200.0,
      "recipient_name": "PREMIER SCAFFOLD, INC."
    },
    {
      "id": 1864987,
      "subaward_number": "52P402182-1",
      "description": "DIRECT EQUIPMENT RENTAL",
      "action_date": "2022-12-12",
      "amount": 31019.0,
      "recipient_name": "UNITED RENTALS (NORTH AMERICA), INC."
    },
    {
      "id": 1868886,
      "subaward_number": "52P401808-0",
      "description": "DIRECT MATERIAL EXPENSE",
      "action_date": "2022-04-29",
      "amount": 30820.0,
      "recipient_name": "M.S.M. INDUSTRIES, INC."
    },
    {
      "id": 56076,
      "subaward_number": "52P402346-18",
      "description": "DIRECT SUBCONTRACT COSTS",
      "action_date": "2023-05-16",
      "amount": 30122.5,
      "recipient_name": "SOUTH BAY SAND BLASTING AND TANK CLEANING, INC."
    },
    {
      "id": 46306,
      "subaward_number": "52P402238-1",
      "description": "DIRECT SUBCONTRACT COSTS",
      "action_date": "2024-11-15",
      "amount": 29970.0,
      "recipient_name": "WESS TRANSPORTATION SERVICES, INC."
    },
    {
      "id": 50480,
      "subaward_number": "52P403199-3",
      "description": "DIRECT SUBCONTRACT COSTS",
      "action_date": "2023-08-21",
      "amount": 29221.0,
      "recipient_name": "IN-PLACE MACHINING COMPANY, LLC"
    },
    {
      "id": 1871061,
      "subaward_number": "52P408624-7",
      "description": "DIRECT SUBCONTRACT COSTS",
      "action_date": "2024-02-13",
      "amount": 28047.6,
      "recipient_name": "BOB TURNER'S CRANE SERVICE INCORPORATED"
    },
    {
      "id": 49356,
      "subaward_number": "52P403020-5",
      "description": "DIRECT SUBCONTRACT COSTS",
      "action_date": "2023-08-03",
      "amount": 27845.0,
      "recipient_name": "PROPULSION CONTROLS ENGINEERING"
    },
    {
      "id": 57086,
      "subaward_number": "52P402346-45",
      "description": "DIRECT SUBCONTRACT COSTS",
      "action_date": "2024-02-12",
      "amount": 27757.4,
      "recipient_name": "SOUTH BAY SAND BLASTING AND TANK CLEANING, INC."
    },
    {
      "id": 57941,
      "subaward_number": "52P402346-34",
      "description": "DIRECT SUBCONTRACT COSTS",
      "action_date": "2023-10-24",
      "amount": 27699.5,
      "recipient_name": "SOUTH BAY SAND BLASTING AND TANK CLEANING, INC."
    },
    {
      "id": 56821,
      "subaward_number": "52P402346-32",
      "description": "DIRECT SUBCONTRACT COSTS",
      "action_date": "2023-10-02",
      "amount": 27699.5,
      "recipient_name": "SOUTH BAY SAND BLASTING AND TANK CLEANING, INC."
    },
    {
      "id": 1863627,
      "subaward_number": "52P410644-2",
      "description": "DIRECT EQUIPMENT RENTAL",
      "action_date": "2024-05-16",
      "amount": 27338.75,
      "recipient_name": "UNITED RENTALS (NORTH AMERICA), INC."
    },
    {
      "id": 1867226,
      "subaward_number": "52P402958-8",
      "description": "DIRECT SUBCONTRACT COSTS",
      "action_date": "2023-07-20",
      "amount": 27256.0,
      "recipient_name": "JOHNSON CONTROLS FEDERAL SYSTEMS, LLC"
    },
    {
      "id": 45626,
      "subaward_number": "52P402933-27",
      "description": "DIRECT SUBCONTRACT COSTS",
      "action_date": "2023-05-19",
      "amount": 26200.0,
      "recipient_name": "PREMIER SCAFFOLD, INC."
    },
    {
      "id": 59887,
      "subaward_number": "52P402346-6",
      "description": "DIRECT SUBCONTRACT COSTS",
      "action_date": "2023-01-05",
      "amount": 25791.0,
      "recipient_name": "SOUTH BAY SAND BLASTING AND TANK CLEANING, INC."
    },
    {
      "id": 57108,
      "subaward_number": "52P403011-3",
      "description": "DIRECT SUBCONTRACT COSTS",
      "action_date": "2024-02-06",
      "amount": 24871.68,
      "recipient_name": "RIX INDUSTRIES"
    },
    {
      "id": 1868764,
      "subaward_number": "52P402345-2",
      "description": "DIRECT SUBCONTRACT COSTS",
      "action_date": "2023-08-23",
      "amount": 24420.0,
      "recipient_name": "PHOENIX INTERNATIONAL HOLDINGS, INC."
    },
    {
      "id": 65228,
      "subaward_number": "52P403095-10",
      "description": "DIRECT SUBCONTRACT COSTS",
      "action_date": "2023-03-07",
      "amount": 24255.0,
      "recipient_name": "SITTA, PAIGE & ASSOCIATES, INC."
    },
    {
      "id": 1873738,
      "subaward_number": "52P403095-18",
      "description": "DIRECT SUBCONTRACT COSTS",
      "action_date": "2023-07-10",
      "amount": 24200.0,
      "recipient_name": "SITTA, PAIGE & ASSOCIATES, INC."
    },
    {
      "id": 45888,
      "subaward_number": "52P403092-7",
      "description": "DIRECT SUBCONTRACT COSTS",
      "action_date": "2024-01-02",
      "amount": 23915.0,
      "recipient_name": "PRIME TIME COATINGS  INC"
    },
    {
      "id": 1869903,
      "subaward_number": "52P402249-11",
      "description": "DIRECT SUBCONTRACT COSTS",
      "action_date": "2023-08-18",
      "amount": 23562.64,
      "recipient_name": "L3HARRIS MARITIME SERVICES INC"
    },
    {
      "id": 45822,
      "subaward_number": "52P402933-44",
      "description": "DIRECT SUBCONTRACT COSTS",
      "action_date": "2023-12-07",
      "amount": 23460.0,
      "recipient_name": "PREMIER SCAFFOLD, INC."
    },
    {
      "id": 60576,
      "subaward_number": "52P403011-4",
      "description": "DIRECT SUBCONTRACT COSTS",
      "action_date": "2024-02-19",
      "amount": 23408.64,
      "recipient_name": "RIX INDUSTRIES"
    },
    {
      "id": 58823,
      "subaward_number": "52P402958-10",
      "description": "DIRECT SUBCONTRACT COSTS",
      "action_date": "2023-10-25",
      "amount": 23130.0,
      "recipient_name": "JOHNSON CONTROLS BUILDING AUTOMATION SYSTEMS, LLC"
    },
    {
      "id": 58794,
      "subaward_number": "52P402346-22",
      "description": "DIRECT SUBCONTRACT COSTS",
      "action_date": "2023-07-14",
      "amount": 22841.5,
      "recipient_name": "SOUTH BAY SAND BLASTING AND TANK CLEANING, INC."
    },
    {
      "id": 49577,
      "subaward_number": "52P402933-22",
      "description": "DIRECT SUBCONTRACT COSTS",
      "action_date": "2023-03-20",
      "amount": 22600.0,
      "recipient_name": "PREMIER SCAFFOLD, INC."
    },
    {
      "id": 1866957,
      "subaward_number": "52P402958-3",
      "description": "DIRECT SUBCONTRACT COSTS",
      "action_date": "2023-01-20",
      "amount": 22548.0,
      "recipient_name": "JOHNSON CONTROLS FEDERAL SYSTEMS, LLC"
    },
    {
      "id": 54480,
      "subaward_number": "52P402346-19",
      "description": "DIRECT SUBCONTRACT COSTS",
      "action_date": "2023-05-18",
      "amount": 22251.0,
      "recipient_name": "SOUTH BAY SAND BLASTING AND TANK CLEANING, INC."
    },
    {
      "id": 58076,
      "subaward_number": "52P402346-23",
      "description": "DIRECT SUBCONTRACT COSTS",
      "action_date": "2023-07-21",
      "amount": 22121.75,
      "recipient_name": "SOUTH BAY SAND BLASTING AND TANK CLEANING, INC."
    },
    {
      "id": 58424,
      "subaward_number": "52P402958-6",
      "description": "DIRECT SUBCONTRACT COSTS",
      "action_date": "2023-06-09",
      "amount": 20328.0,
      "recipient_name": "JOHNSON CONTROLS BUILDING AUTOMATION SYSTEMS, LLC"
    },
    {
      "id": 1869361,
      "subaward_number": "52P402345-3",
      "description": "DIRECT SUBCONTRACT COSTS",
      "action_date": "2023-12-11",
      "amount": 20158.0,
      "recipient_name": "PHOENIX INTERNATIONAL HOLDINGS, INC."
    },
    {
      "id": 9576918,
      "subaward_number": "52P406544-2",
      "description": "DIRECT SUBCONTRACT COSTS",
      "action_date": "2023-11-29",
      "amount": 20000.0,
      "recipient_name": "CLEAN HARBORS ENVIRONMENTAL SERVICES INC"
    },
    {
      "id": 53642,
      "subaward_number": "52P402346-17",
      "description": "DIRECT SUBCONTRACT COSTS",
      "action_date": "2023-05-15",
      "amount": 19945.75,
      "recipient_name": "SOUTH BAY SAND BLASTING AND TANK CLEANING, INC."
    },
    {
      "id": 65057,
      "subaward_number": "52P403095-23",
      "description": "DIRECT SUBCONTRACT COSTS",
      "action_date": "2023-09-01",
      "amount": 19436.5,
      "recipient_name": "SITTA, PAIGE & ASSOCIATES, INC."
    },
    {
      "id": 1863766,
      "subaward_number": "52P403366-3",
      "description": "DIRECT EQUIPMENT RENTAL",
      "action_date": "2023-10-20",
      "amount": 19404.63,
      "recipient_name": "UNITED RENTALS (NORTH AMERICA), INC."
    },
    {
      "id": 56910,
      "subaward_number": "52P402346-28",
      "description": "DIRECT SUBCONTRACT COSTS",
      "action_date": "2023-08-23",
      "amount": 18367.5,
      "recipient_name": "SOUTH BAY SAND BLASTING AND TANK CLEANING, INC."
    },
    {
      "id": 1868199,
      "subaward_number": "52P408624-4",
      "description": "DIRECT SUBCONTRACT COSTS",
      "action_date": "2023-12-21",
      "amount": 18099.2,
      "recipient_name": "BOB TURNER'S CRANE SERVICE INCORPORATED"
    },
    {
      "id": 56995,
      "subaward_number": "52P402346-29",
      "description": "DIRECT SUBCONTRACT COSTS",
      "action_date": "2023-09-14",
      "amount": 16491.25,
      "recipient_name": "SOUTH BAY SAND BLASTING AND TANK CLEANING, INC."
    },
    {
      "id": 46679,
      "subaward_number": "52P402933-19",
      "description": "DIRECT SUBCONTRACT COSTS",
      "action_date": "2023-02-10",
      "amount": 15840.0,
      "recipient_name": "PREMIER SCAFFOLD, INC."
    },
    {
      "id": 59281,
      "subaward_number": "52P402346-24",
      "description": "DIRECT SUBCONTRACT COSTS",
      "action_date": "2023-07-24",
      "amount": 15453.75,
      "recipient_name": "SOUTH BAY SAND BLASTING AND TANK CLEANING, INC."
    },
    {
      "id": 49661,
      "subaward_number": "52P402933-13",
      "description": "DIRECT SUBCONTRACT COSTS",
      "action_date": "2023-01-17",
      "amount": 15156.0,
      "recipient_name": "PREMIER SCAFFOLD, INC."
    },
    {
      "id": 59315,
      "subaward_number": "52P402346-15",
      "description": "DIRECT SUBCONTRACT COSTS",
      "action_date": "2023-05-03",
      "amount": 14908.0,
      "recipient_name": "SOUTH BAY SAND BLASTING AND TANK CLEANING, INC."
    },
    {
      "id": 1868847,
      "subaward_number": "52P402737-15",
      "description": "DIRECT SUBCONTRACT COSTS",
      "action_date": "2023-06-05",
      "amount": 14399.0,
      "recipient_name": "AMP UNITED LLC"
    },
    {
      "id": 1868745,
      "subaward_number": "52P402737-13",
      "description": "DIRECT SUBCONTRACT COSTS",
      "action_date": "2023-05-24",
      "amount": 14399.0,
      "recipient_name": "AMP UNITED LLC"
    },
    {
      "id": 53352,
      "subaward_number": "52P402933-28",
      "description": "DIRECT SUBCONTRACT COSTS",
      "action_date": "2023-06-05",
      "amount": 13600.0,
      "recipient_name": "PREMIER SCAFFOLD, INC."
    },
    {
      "id": 55473,
      "subaward_number": "52P402986-15",
      "description": "DIRECT SUBCONTRACT COSTS",
      "action_date": "2023-10-16",
      "amount": 13500.0,
      "recipient_name": "IMIA, LLC"
    },
    {
      "id": 59729,
      "subaward_number": "52P402986-13",
      "description": "DIRECT SUBCONTRACT COSTS",
      "action_date": "2023-07-17",
      "amount": 13000.0,
      "recipient_name": "IMIA, LLC"
    },
    {
      "id": 57729,
      "subaward_number": "52P403698-1",
      "description": "DIRECT SUBCONTRACT COSTS",
      "action_date": "2023-07-14",
      "amount": 13000.0,
      "recipient_name": "ALFA LAVAL INC"
    },
    {
      "id": 46970,
      "subaward_number": "52P403698-2",
      "description": "DIRECT SUBCONTRACT COSTS",
      "action_date": "2023-08-08",
      "amount": 13000.0,
      "recipient_name": "ALFA LAVAL INC"
    },
    {
      "id": 51399,
      "subaward_number": "52P402933-35",
      "description": "DIRECT SUBCONTRACT COSTS",
      "action_date": "2023-08-18",
      "amount": 12900.0,
      "recipient_name": "PREMIER SCAFFOLD, INC."
    },
    {
      "id": 46140,
      "subaward_number": "52P402933-37",
      "description": "DIRECT SUBCONTRACT COSTS",
      "action_date": "2023-09-26",
      "amount": 12682.0,
      "recipient_name": "PREMIER SCAFFOLD, INC."
    },
    {
      "id": 46558,
      "subaward_number": "52P402933-18",
      "description": "DIRECT SUBCONTRACT COSTS",
      "action_date": "2023-02-07",
      "amount": 12672.0,
      "recipient_name": "PREMIER SCAFFOLD, INC."
    },
    {
      "id": 56386,
      "subaward_number": "52P402346-13",
      "description": "DIRECT SUBCONTRACT COSTS",
      "action_date": "2023-04-07",
      "amount": 12506.0,
      "recipient_name": "SOUTH BAY SAND BLASTING AND TANK CLEANING, INC."
    },
    {
      "id": 58534,
      "subaward_number": "52P402346-27",
      "description": "DIRECT SUBCONTRACT COSTS",
      "action_date": "2023-08-16",
      "amount": 12321.25,
      "recipient_name": "SOUTH BAY SAND BLASTING AND TANK CLEANING, INC."
    },
    {
      "id": 1864841,
      "subaward_number": "52P403366-1",
      "description": "DIRECT EQUIPMENT RENTAL",
      "action_date": "2023-02-20",
      "amount": 12045.34,
      "recipient_name": "UNITED RENTALS (NORTH AMERICA), INC."
    },
    {
      "id": 48767,
      "subaward_number": "52P402933-33",
      "description": "DIRECT SUBCONTRACT COSTS",
      "action_date": "2023-08-02",
      "amount": 11980.0,
      "recipient_name": "PREMIER SCAFFOLD, INC."
    },
    {
      "id": 1867915,
      "subaward_number": "52P402249-15",
      "description": "DIRECT SUBCONTRACT COSTS",
      "action_date": "2024-01-24",
      "amount": 11714.0,
      "recipient_name": "L3HARRIS MARITIME SERVICES INC"
    },
    {
      "id": 50107,
      "subaward_number": "52P402933-31",
      "description": "DIRECT SUBCONTRACT COSTS",
      "action_date": "2023-07-17",
      "amount": 11580.0,
      "recipient_name": "PREMIER SCAFFOLD, INC."
    },
    {
      "id": 1864083,
      "subaward_number": "52P402182-3",
      "description": "DIRECT EQUIPMENT RENTAL",
      "action_date": "2023-06-22",
      "amount": 11564.03,
      "recipient_name": "UNITED RENTALS NORTH AMERICA INC"
    },
    {
      "id": 48751,
      "subaward_number": "52P402933-21",
      "description": "DIRECT SUBCONTRACT COSTS",
      "action_date": "2023-03-01",
      "amount": 11280.0,
      "recipient_name": "PREMIER SCAFFOLD, INC."
    },
    {
      "id": 58320,
      "subaward_number": "52P402986-9",
      "description": "DIRECT SUBCONTRACT COSTS",
      "action_date": "2023-03-21",
      "amount": 11030.0,
      "recipient_name": "IMIA, LLC"
    },
    {
      "id": 1872350,
      "subaward_number": "52P403095-30",
      "description": "DIRECT SUBCONTRACT COSTS",
      "action_date": "2023-10-24",
      "amount": 10874.0,
      "recipient_name": "SITTA, PAIGE & ASSOCIATES, INC."
    },
    {
      "id": 1864557,
      "subaward_number": "52P403366-4",
      "description": "DIRECT EQUIPMENT RENTAL",
      "action_date": "2024-04-22",
      "amount": 10694.16,
      "recipient_name": "UNITED RENTALS (NORTH AMERICA), INC."
    },
    {
      "id": 51761,
      "subaward_number": "52P402715-1",
      "description": "DIRECT SUBCONTRACT COSTS",
      "action_date": "2023-10-24",
      "amount": 10569.6,
      "recipient_name": "JAL ENTERPRISES, INC."
    },
    {
      "id": 9576919,
      "subaward_number": "52P406544-3",
      "description": "DIRECT SUBCONTRACT COSTS",
      "action_date": "2024-04-03",
      "amount": 10500.0,
      "recipient_name": "CLEAN HARBORS ENVIRONMENTAL SERVICES INC"
    },
    {
      "id": 47862,
      "subaward_number": "52P403092-2",
      "description": "DIRECT SUBCONTRACT COSTS",
      "action_date": "2023-02-01",
      "amount": 10430.0,
      "recipient_name": "PRIME TIME COATINGS  INC"
    },
    {
      "id": 9576917,
      "subaward_number": "52P406544-1",
      "description": "DIRECT SUBCONTRACT COSTS",
      "action_date": "2023-08-28",
      "amount": 10000.0,
      "recipient_name": "CLEAN HARBORS ENVIRONMENTAL SERVICES INC"
    },
    {
      "id": 55474,
      "subaward_number": "52P402986-14",
      "description": "DIRECT SUBCONTRACT COSTS",
      "action_date": "2023-09-12",
      "amount": 9990.0,
      "recipient_name": "IMIA, LLC"
    },
    {
      "id": 56094,
      "subaward_number": "52P402346-31",
      "description": "DIRECT SUBCONTRACT COSTS",
      "action_date": "2023-09-27",
      "amount": 9909.25,
      "recipient_name": "SOUTH BAY SAND BLASTING AND TANK CLEANING, INC."
    },
    {
      "id": 1869037,
      "subaward_number": "52P402249-8",
      "description": "DIRECT SUBCONTRACT COSTS",
      "action_date": "2023-05-24",
      "amount": 9892.0,
      "recipient_name": "L3HARRIS MARITIME SERVICES INC"
    },
    {
      "id": 59908,
      "subaward_number": "52P403021-6",
      "description": "DIRECT SUBCONTRACT COSTS",
      "action_date": "2023-03-07",
      "amount": 9520.0,
      "recipient_name": "TOM GARCIA, INC"
    },
    {
      "id": 49283,
      "subaward_number": "52P402933-25",
      "description": "DIRECT SUBCONTRACT COSTS",
      "action_date": "2023-05-11",
      "amount": 9500.0,
      "recipient_name": "PREMIER SCAFFOLD, INC."
    },
    {
      "id": 59222,
      "subaward_number": "52P402986-17",
      "description": "DIRECT SUBCONTRACT COSTS",
      "action_date": "2023-11-30",
      "amount": 9400.0,
      "recipient_name": "IMIA, LLC"
    },
    {
      "id": 1874165,
      "subaward_number": "52P403095-9",
      "description": "DIRECT SUBCONTRACT COSTS",
      "action_date": "2023-01-18",
      "amount": 9093.0,
      "recipient_name": "SITTA, PAIGE & ASSOCIATES, INC."
    },
    {
      "id": 1864374,
      "subaward_number": "52P402182-2",
      "description": "DIRECT EQUIPMENT RENTAL",
      "action_date": "2023-04-07",
      "amount": 9027.24,
      "recipient_name": "UNITED RENTALS (NORTH AMERICA), INC."
    },
    {
      "id": 49431,
      "subaward_number": "52P403020-4",
      "description": "DIRECT SUBCONTRACT COSTS",
      "action_date": "2023-07-24",
      "amount": 8998.0,
      "recipient_name": "PROPULSION CONTROLS ENGINEERING"
    },
    {
      "id": 46934,
      "subaward_number": "52P403092-4",
      "description": "DIRECT SUBCONTRACT COSTS",
      "action_date": "2023-11-02",
      "amount": 8970.0,
      "recipient_name": "PRIME TIME COATINGS  INC"
    },
    {
      "id": 1870471,
      "subaward_number": "52P402249-10",
      "description": "DIRECT SUBCONTRACT COSTS",
      "action_date": "2023-08-08",
      "amount": 8598.0,
      "recipient_name": "L3HARRIS MARITIME SERVICES INC"
    },
    {
      "id": 1864820,
      "subaward_number": "52P402302-4",
      "description": "DIRECT EQUIPMENT RENTAL",
      "action_date": "2023-05-04",
      "amount": 8569.72,
      "recipient_name": "UNITED RENTALS (NORTH AMERICA), INC."
    },
    {
      "id": 61094,
      "subaward_number": "52P402986-12",
      "description": "DIRECT SUBCONTRACT COSTS",
      "action_date": "2023-06-06",
      "amount": 7980.0,
      "recipient_name": "IMIA, LLC"
    },
    {
      "id": 1863583,
      "subaward_number": "52P403766-1",
      "description": "DIRECT EQUIPMENT RENTAL",
      "action_date": "2023-02-09",
      "amount": 7936.7,
      "recipient_name": "UNITED RENTALS (NORTH AMERICA), INC."
    },
    {
      "id": 1869331,
      "subaward_number": "52P402737-16",
      "description": "DIRECT SUBCONTRACT COSTS",
      "action_date": "2023-06-14",
      "amount": 7853.0,
      "recipient_name": "AMP UNITED LLC"
    },
    {
      "id": 1873915,
      "subaward_number": "52P403095-20",
      "description": "DIRECT SUBCONTRACT COSTS",
      "action_date": "2023-07-17",
      "amount": 7844.68,
      "recipient_name": "SITTA, PAIGE & ASSOCIATES, INC."
    },
    {
      "id": 62346,
      "subaward_number": "52P403812-2",
      "description": "DIRECT EQUIPMENT RENTAL",
      "action_date": "2023-06-23",
      "amount": 7775.67,
      "recipient_name": "RED-D-ARC INC"
    },
    {
      "id": 1868091,
      "subaward_number": "52P401690-2",
      "description": "DIRECT SUBCONTRACT COSTS",
      "action_date": "2023-08-09",
      "amount": 7691.0,
      "recipient_name": "OCKERMAN AUTOMATION CONSULTING INC"
    },
    {
      "id": 1864360,
      "subaward_number": "52P402302-6",
      "description": "DIRECT EQUIPMENT RENTAL",
      "action_date": "2023-06-16",
      "amount": 7613.86,
      "recipient_name": "UNITED RENTALS NORTH AMERICA INC"
    },
    {
      "id": 1863905,
      "subaward_number": "52P402302-5",
      "description": "DIRECT EQUIPMENT RENTAL",
      "action_date": "2023-05-05",
      "amount": 7613.86,
      "recipient_name": "UNITED RENTALS (NORTH AMERICA), INC."
    },
    {
      "id": 64747,
      "subaward_number": "52P403095-27",
      "description": "DIRECT SUBCONTRACT COSTS",
      "action_date": "2023-09-25",
      "amount": 7500.0,
      "recipient_name": "SITTA, PAIGE & ASSOCIATES, INC."
    },
    {
      "id": 48175,
      "subaward_number": "52P403020-6",
      "description": "DIRECT SUBCONTRACT COSTS",
      "action_date": "2023-12-18",
      "amount": 7500.0,
      "recipient_name": "PROPULSION CONTROLS ENGINEERING"
    },
    {
      "id": 1871742,
      "subaward_number": "52P403095-16",
      "description": "DIRECT SUBCONTRACT COSTS",
      "action_date": "2023-06-26",
      "amount": 7365.74,
      "recipient_name": "SITTA, PAIGE & ASSOCIATES, INC."
    },
    {
      "id": 50144,
      "subaward_number": "52P402933-47",
      "description": "DIRECT SUBCONTRACT COSTS",
      "action_date": "2024-01-05",
      "amount": 7360.0,
      "recipient_name": "PREMIER SCAFFOLD, INC."
    },
    {
      "id": 57658,
      "subaward_number": "52P402986-16",
      "description": "DIRECT SUBCONTRACT COSTS",
      "action_date": "2023-11-28",
      "amount": 7320.0,
      "recipient_name": "IMIA, LLC"
    },
    {
      "id": 1869474,
      "subaward_number": "52P408624-3",
      "description": "DIRECT SUBCONTRACT COSTS",
      "action_date": "2023-12-11",
      "amount": 7246.4,
      "recipient_name": "BOB TURNER'S CRANE SERVICE INCORPORATED"
    },
    {
      "id": 1868522,
      "subaward_number": "52P402249-16",
      "description": "DIRECT SUBCONTRACT COSTS",
      "action_date": "2024-02-02",
      "amount": 7200.0,
      "recipient_name": "L3HARRIS MARITIME SERVICES INC"
    },
    {
      "id": 50330,
      "subaward_number": "52P402933-24",
      "description": "DIRECT SUBCONTRACT COSTS",
      "action_date": "2023-05-03",
      "amount": 7200.0,
      "recipient_name": "PREMIER SCAFFOLD, INC."
    },
    {
      "id": 62582,
      "subaward_number": "52P403812-5",
      "description": "DIRECT MATERIAL EXPENSE",
      "action_date": "2024-04-11",
      "amount": 7155.57,
      "recipient_name": "RED-D-ARC INC"
    },
    {
      "id": 1872903,
      "subaward_number": "52P404259-3",
      "description": "DIRECT SUBCONTRACT COSTS",
      "action_date": "2024-09-06",
      "amount": 7150.0,
      "recipient_name": "INSPEC TESTING, INC."
    },
    {
      "id": 52231,
      "subaward_number": "52P402933-40",
      "description": "DIRECT SUBCONTRACT COSTS",
      "action_date": "2023-10-19",
      "amount": 6860.0,
      "recipient_name": "PREMIER SCAFFOLD, INC."
    },
    {
      "id": 1866095,
      "subaward_number": "52P402958-5",
      "description": "DIRECT SUBCONTRACT COSTS",
      "action_date": "2023-02-06",
      "amount": 6774.0,
      "recipient_name": "JOHNSON CONTROLS FEDERAL SYSTEMS, LLC"
    },
    {
      "id": 63451,
      "subaward_number": "52P402737-10",
      "description": "DIRECT SUBCONTRACT COSTS",
      "action_date": "2023-05-03",
      "amount": 6432.0,
      "recipient_name": "AMP UNITED LLC"
    },
    {
      "id": 62205,
      "subaward_number": "52P402737-11",
      "description": "DIRECT SUBCONTRACT COSTS",
      "action_date": "2023-05-15",
      "amount": 6432.0,
      "recipient_name": "AMP UNITED LLC"
    },
    {
      "id": 61449,
      "subaward_number": "52P402346-20",
      "description": "DIRECT SUBCONTRACT COSTS",
      "action_date": "2023-05-26",
      "amount": 6325.0,
      "recipient_name": "SOUTH BAY SAND BLASTING AND TANK CLEANING, INC."
    },
    {
      "id": 58309,
      "subaward_number": "52P402346-16",
      "description": "DIRECT SUBCONTRACT COSTS",
      "action_date": "2023-05-08",
      "amount": 6325.0,
      "recipient_name": "SOUTH BAY SAND BLASTING AND TANK CLEANING, INC."
    },
    {
      "id": 1863675,
      "subaward_number": "52P403366-2",
      "description": "DIRECT EQUIPMENT RENTAL",
      "action_date": "2023-06-22",
      "amount": 6015.49,
      "recipient_name": "UNITED RENTALS NORTH AMERICA INC"
    },
    {
      "id": 1869555,
      "subaward_number": "52P408624-5",
      "description": "DIRECT SUBCONTRACT COSTS",
      "action_date": "2024-01-08",
      "amount": 5885.6,
      "recipient_name": "BOB TURNER'S CRANE SERVICE INCORPORATED"
    },
    {
      "id": 49336,
      "subaward_number": "52P402933-23",
      "description": "DIRECT SUBCONTRACT COSTS",
      "action_date": "2023-04-20",
      "amount": 5700.0,
      "recipient_name": "PREMIER SCAFFOLD, INC."
    },
    {
      "id": 55192,
      "subaward_number": "52P402986-11",
      "description": "DIRECT SUBCONTRACT COSTS",
      "action_date": "2023-06-05",
      "amount": 5350.0,
      "recipient_name": "IMIA, LLC"
    },
    {
      "id": 1865147,
      "subaward_number": "52P404333-1",
      "description": "DIRECT EQUIPMENT RENTAL",
      "action_date": "2023-05-24",
      "amount": 5321.4,
      "recipient_name": "UNITED RENTALS (NORTH AMERICA), INC."
    },
    {
      "id": 54576,
      "subaward_number": "52P402346-42",
      "description": "DIRECT SUBCONTRACT COSTS",
      "action_date": "2024-01-05",
      "amount": 5089.25,
      "recipient_name": "SOUTH BAY SAND BLASTING AND TANK CLEANING, INC."
    },
    {
      "id": 63546,
      "subaward_number": "52P402737-12",
      "description": "DIRECT SUBCONTRACT COSTS",
      "action_date": "2023-05-16",
      "amount": 5070.0,
      "recipient_name": "AMP UNITED LLC"
    },
    {
      "id": 1870241,
      "subaward_number": "52P402249-6",
      "description": "DIRECT SUBCONTRACT COSTS",
      "action_date": "2023-05-18",
      "amount": 4990.0,
      "recipient_name": "L3HARRIS MARITIME SERVICES INC"
    },
    {
      "id": 50335,
      "subaward_number": "52P402933-43",
      "description": "DIRECT SUBCONTRACT COSTS",
      "action_date": "2023-12-06",
      "amount": 4920.0,
      "recipient_name": "PREMIER SCAFFOLD, INC."
    },
    {
      "id": 59564,
      "subaward_number": "52P402346-9",
      "description": "DIRECT SUBCONTRACT COSTS",
      "action_date": "2023-02-27",
      "amount": 4676.0,
      "recipient_name": "SOUTH BAY SAND BLASTING AND TANK CLEANING, INC."
    },
    {
      "id": 1863959,
      "subaward_number": "52P402182-4",
      "description": "DIRECT EQUIPMENT RENTAL",
      "action_date": "2023-06-27",
      "amount": 4376.48,
      "recipient_name": "UNITED RENTALS NORTH AMERICA INC"
    },
    {
      "id": 1871487,
      "subaward_number": "52P403095-31",
      "description": "DIRECT SUBCONTRACT COSTS",
      "action_date": "2023-11-28",
      "amount": 4345.0,
      "recipient_name": "SITTA, PAIGE & ASSOCIATES, INC."
    },
    {
      "id": 1872297,
      "subaward_number": "52P403095-14",
      "description": "DIRECT SUBCONTRACT COSTS",
      "action_date": "2023-06-12",
      "amount": 4279.62,
      "recipient_name": "SITTA, PAIGE & ASSOCIATES, INC."
    },
    {
      "id": 48384,
      "subaward_number": "52P402933-49",
      "description": "DIRECT SUBCONTRACT COSTS",
      "action_date": "2024-02-07",
      "amount": 4240.0,
      "recipient_name": "PREMIER SCAFFOLD, INC."
    },
    {
      "id": 1864460,
      "subaward_number": "52P403410-2",
      "description": "DIRECT EQUIPMENT RENTAL",
      "action_date": "2023-04-19",
      "amount": 4233.47,
      "recipient_name": "UNITED RENTALS (NORTH AMERICA), INC."
    },
    {
      "id": 62493,
      "subaward_number": "52P403248-11",
      "description": "DIRECT SUBCONTRACT COSTS",
      "action_date": "2023-05-05",
      "amount": 4128.0,
      "recipient_name": "L3HARRIS MARITIME SERVICES INC"
    },
    {
      "id": 57573,
      "subaward_number": "52P402346-35",
      "description": "DIRECT SUBCONTRACT COSTS",
      "action_date": "2023-10-25",
      "amount": 4052.5,
      "recipient_name": "SOUTH BAY SAND BLASTING AND TANK CLEANING, INC."
    },
    {
      "id": 1871806,
      "subaward_number": "52P403095-29",
      "description": "DIRECT SUBCONTRACT COSTS",
      "action_date": "2023-10-17",
      "amount": 4023.46,
      "recipient_name": "SITTA, PAIGE & ASSOCIATES, INC."
    },
    {
      "id": 1864394,
      "subaward_number": "52P409128-1",
      "description": "DIRECT EQUIPMENT RENTAL",
      "action_date": "2024-04-23",
      "amount": 3997.11,
      "recipient_name": "UNITED RENTALS (NORTH AMERICA), INC."
    },
    {
      "id": 61069,
      "subaward_number": "52P402986-18",
      "description": "DIRECT SUBCONTRACT COSTS",
      "action_date": "2023-12-21",
      "amount": 3994.83,
      "recipient_name": "IMIA, LLC"
    },
    {
      "id": 1864034,
      "subaward_number": "52P403766-3",
      "description": "DIRECT EQUIPMENT RENTAL",
      "action_date": "2023-05-10",
      "amount": 3976.54,
      "recipient_name": "UNITED RENTALS (NORTH AMERICA), INC."
    },
    {
      "id": 1863594,
      "subaward_number": "52P403766-2",
      "description": "DIRECT EQUIPMENT RENTAL",
      "action_date": "2023-04-10",
      "amount": 3973.94,
      "recipient_name": "UNITED RENTALS (NORTH AMERICA), INC."
    },
    {
      "id": 1866763,
      "subaward_number": "52P402958-7",
      "description": "DIRECT SUBCONTRACT COSTS",
      "action_date": "2023-07-10",
      "amount": 3968.0,
      "recipient_name": "JOHNSON CONTROLS FEDERAL SYSTEMS, LLC"
    },
    {
      "id": 53968,
      "subaward_number": "52P402986-8",
      "description": "DIRECT SUBCONTRACT COSTS",
      "action_date": "2023-02-26",
      "amount": 3940.0,
      "recipient_name": "IMIA, LLC"
    },
    {
      "id": 52414,
      "subaward_number": "52P402933-48",
      "description": "DIRECT SUBCONTRACT COSTS",
      "action_date": "2024-01-24",
      "amount": 3920.0,
      "recipient_name": "PREMIER SCAFFOLD, INC."
    },
    {
      "id": 51680,
      "subaward_number": "52P402933-38",
      "description": "DIRECT SUBCONTRACT COSTS",
      "action_date": "2023-10-02",
      "amount": 3800.0,
      "recipient_name": "PREMIER SCAFFOLD, INC."
    },
    {
      "id": 54800,
      "subaward_number": "52P402346-7",
      "description": "DIRECT SUBCONTRACT COSTS",
      "action_date": "2023-02-06",
      "amount": 3796.0,
      "recipient_name": "SOUTH BAY SAND BLASTING AND TANK CLEANING, INC."
    },
    {
      "id": 59248,
      "subaward_number": "52P402986-5",
      "description": "DIRECT SUBCONTRACT COSTS",
      "action_date": "2023-01-06",
      "amount": 3777.0,
      "recipient_name": "IMIA, LLC"
    },
    {
      "id": 50019,
      "subaward_number": "52P402933-45",
      "description": "DIRECT SUBCONTRACT COSTS",
      "action_date": "2023-12-12",
      "amount": 3710.0,
      "recipient_name": "PREMIER SCAFFOLD, INC."
    },
    {
      "id": 48804,
      "subaward_number": "52P402933-29",
      "description": "DIRECT SUBCONTRACT COSTS",
      "action_date": "2023-06-13",
      "amount": 3610.0,
      "recipient_name": "PREMIER SCAFFOLD, INC."
    },
    {
      "id": 1873979,
      "subaward_number": "52P403095-13",
      "description": "DIRECT SUBCONTRACT COSTS",
      "action_date": "2023-05-22",
      "amount": 3589.42,
      "recipient_name": "SITTA, PAIGE & ASSOCIATES, INC."
    },
    {
      "id": 58802,
      "subaward_number": "52P402346-43",
      "description": "DIRECT SUBCONTRACT COSTS",
      "action_date": "2024-01-16",
      "amount": 3510.25,
      "recipient_name": "SOUTH BAY SAND BLASTING AND TANK CLEANING, INC."
    },
    {
      "id": 62153,
      "subaward_number": "52P403812-4",
      "description": "DIRECT MATERIAL EXPENSE",
      "action_date": "2024-01-12",
      "amount": 3297.13,
      "recipient_name": "RED-D-ARC INC"
    },
    {
      "id": 61125,
      "subaward_number": "52P402986-10",
      "description": "DIRECT SUBCONTRACT COSTS",
      "action_date": "2023-05-15",
      "amount": 3281.0,
      "recipient_name": "IMIA, LLC"
    },
    {
      "id": 1868396,
      "subaward_number": "52P402249-13",
      "description": "DIRECT SUBCONTRACT COSTS",
      "action_date": "2023-11-28",
      "amount": 3176.0,
      "recipient_name": "L3HARRIS MARITIME SERVICES INC"
    },
    {
      "id": 46711,
      "subaward_number": "52P402933-12",
      "description": "DIRECT SUBCONTRACT COSTS",
      "action_date": "2023-01-17",
      "amount": 3168.0,
      "recipient_name": "PREMIER SCAFFOLD, INC."
    },
    {
      "id": 45474,
      "subaward_number": "52P402933-17",
      "description": "DIRECT SUBCONTRACT COSTS",
      "action_date": "2023-02-06",
      "amount": 3168.0,
      "recipient_name": "PREMIER SCAFFOLD, INC."
    },
    {
      "id": 46400,
      "subaward_number": "52P402933-41",
      "description": "DIRECT SUBCONTRACT COSTS",
      "action_date": "2023-10-24",
      "amount": 2990.0,
      "recipient_name": "PREMIER SCAFFOLD, INC."
    },
    {
      "id": 59525,
      "subaward_number": "52P402346-25",
      "description": "DIRECT SUBCONTRACT COSTS",
      "action_date": "2023-07-31",
      "amount": 2956.0,
      "recipient_name": "SOUTH BAY SAND BLASTING AND TANK CLEANING, INC."
    },
    {
      "id": 64129,
      "subaward_number": "52P402616-5",
      "description": "DIRECT SUBCONTRACT COSTS",
      "action_date": "2023-04-28",
      "amount": 2829.0,
      "recipient_name": "DEFENSE MARITIME SOLUTIONS, INC."
    },
    {
      "id": 1870349,
      "subaward_number": "52P402249-5",
      "description": "DIRECT SUBCONTRACT COSTS",
      "action_date": "2023-02-28",
      "amount": 2660.0,
      "recipient_name": "L3HARRIS MARITIME SERVICES INC"
    },
    {
      "id": 55487,
      "subaward_number": "52P402346-33",
      "description": "DIRECT SUBCONTRACT COSTS",
      "action_date": "2023-10-18",
      "amount": 2361.0,
      "recipient_name": "SOUTH BAY SAND BLASTING AND TANK CLEANING, INC."
    },
    {
      "id": 1867774,
      "subaward_number": "52P402249-4",
      "description": "DIRECT SUBCONTRACT COSTS",
      "action_date": "2023-01-18",
      "amount": 2209.0,
      "recipient_name": "L3HARRIS MARITIME SERVICES INC"
    },
    {
      "id": 65143,
      "subaward_number": "52P403095-11",
      "description": "DIRECT SUBCONTRACT COSTS",
      "action_date": "2023-03-13",
      "amount": 2126.0,
      "recipient_name": "SITTA, PAIGE & ASSOCIATES, INC."
    },
    {
      "id": 65216,
      "subaward_number": "52P403095-26",
      "description": "DIRECT SUBCONTRACT COSTS",
      "action_date": "2023-09-22",
      "amount": 2016.56,
      "recipient_name": "SITTA, PAIGE & ASSOCIATES, INC."
    },
    {
      "id": 1866453,
      "subaward_number": "52P403326-10",
      "description": "DIRECT SUBCONTRACT COSTS",
      "action_date": "2023-09-25",
      "amount": 1860.0,
      "recipient_name": "STANDARD INSPECTION SERVICES"
    },
    {
      "id": 1871421,
      "subaward_number": "52P403095-17",
      "description": "DIRECT SUBCONTRACT COSTS",
      "action_date": "2023-06-30",
      "amount": 1796.0,
      "recipient_name": "SITTA, PAIGE & ASSOCIATES, INC."
    },
    {
      "id": 61734,
      "subaward_number": "52P402346-37",
      "description": "DIRECT SUBCONTRACT COSTS",
      "action_date": "2023-11-28",
      "amount": 1795.0,
      "recipient_name": "SOUTH BAY SAND BLASTING AND TANK CLEANING, INC."
    },
    {
      "id": 60095,
      "subaward_number": "52P402346-40",
      "description": "DIRECT SUBCONTRACT COSTS",
      "action_date": "2023-12-13",
      "amount": 1795.0,
      "recipient_name": "SOUTH BAY SAND BLASTING AND TANK CLEANING, INC."
    },
    {
      "id": 1872202,
      "subaward_number": "52P403095-19",
      "description": "DIRECT SUBCONTRACT COSTS",
      "action_date": "2023-07-11",
      "amount": 1776.0,
      "recipient_name": "SITTA, PAIGE & ASSOCIATES, INC."
    },
    {
      "id": 61832,
      "subaward_number": "52P402737-7",
      "description": "DIRECT SUBCONTRACT COSTS",
      "action_date": "2023-01-20",
      "amount": 1680.0,
      "recipient_name": "AMP UNITED LLC"
    },
    {
      "id": 1872624,
      "subaward_number": "52P403095-12",
      "description": "DIRECT SUBCONTRACT COSTS",
      "action_date": "2023-04-12",
      "amount": 1488.0,
      "recipient_name": "SITTA, PAIGE & ASSOCIATES, INC."
    },
    {
      "id": 56629,
      "subaward_number": "52P403011-2",
      "description": "DIRECT SUBCONTRACT COSTS",
      "action_date": "2023-08-15",
      "amount": 1463.04,
      "recipient_name": "RIX INDUSTRIES"
    },
    {
      "id": 1872999,
      "subaward_number": "52P404259-1",
      "description": "DIRECT SUBCONTRACT COSTS",
      "action_date": "2023-12-18",
      "amount": 1250.0,
      "recipient_name": "INSPEC TESTING, INC."
    },
    {
      "id": 1874681,
      "subaward_number": "52P403095-28",
      "description": "DIRECT SUBCONTRACT COSTS",
      "action_date": "2023-10-12",
      "amount": 1000.0,
      "recipient_name": "SITTA, PAIGE & ASSOCIATES, INC."
    },
    {
      "id": 62711,
      "subaward_number": "52P403248-12",
      "description": "DIRECT SUBCONTRACT COSTS",
      "action_date": "2024-01-03",
      "amount": 1000.0,
      "recipient_name": "L3HARRIS MARITIME SERVICES INC"
    },
    {
      "id": 59093,
      "subaward_number": "52P403021-7",
      "description": "DIRECT SUBCONTRACT COSTS",
      "action_date": "2023-04-05",
      "amount": 950.0,
      "recipient_name": "TOM GARCIA, INC"
    },
    {
      "id": 1871405,
      "subaward_number": "52P403095-21",
      "description": "DIRECT SUBCONTRACT COSTS",
      "action_date": "2023-07-18",
      "amount": 924.0,
      "recipient_name": "SITTA, PAIGE & ASSOCIATES, INC."
    },
    {
      "id": 1867130,
      "subaward_number": "52P403326-4",
      "description": "DIRECT SUBCONTRACT COSTS",
      "action_date": "2023-01-19",
      "amount": 680.0,
      "recipient_name": "STANDARD INSPECTION SERVICES"
    },
    {
      "id": 1866922,
      "subaward_number": "52P403326-7",
      "description": "DIRECT SUBCONTRACT COSTS",
      "action_date": "2023-02-17",
      "amount": 680.0,
      "recipient_name": "STANDARD INSPECTION SERVICES"
    },
    {
      "id": 1865943,
      "subaward_number": "52P403326-6",
      "description": "DIRECT SUBCONTRACT COSTS",
      "action_date": "2023-02-09",
      "amount": 680.0,
      "recipient_name": "STANDARD INSPECTION SERVICES"
    },
    {
      "id": 1867639,
      "subaward_number": "52P403812-3",
      "description": "DIRECT MATERIAL EXPENSE",
      "action_date": "2023-07-31",
      "amount": 679.17,
      "recipient_name": "RED-D-ARC INC"
    },
    {
      "id": 64556,
      "subaward_number": "52P403095-24",
      "description": "DIRECT SUBCONTRACT COSTS",
      "action_date": "2023-09-07",
      "amount": 565.0,
      "recipient_name": "SITTA, PAIGE & ASSOCIATES, INC."
    },
    {
      "id": 63660,
      "subaward_number": "52P403095-25",
      "description": "DIRECT SUBCONTRACT COSTS",
      "action_date": "2023-09-12",
      "amount": 565.0,
      "recipient_name": "SITTA, PAIGE & ASSOCIATES, INC."
    },
    {
      "id": 1867249,
      "subaward_number": "52P403326-8",
      "description": "DIRECT SUBCONTRACT COSTS",
      "action_date": "2023-05-15",
      "amount": 480.0,
      "recipient_name": "STANDARD INSPECTION SERVICES"
    },
    {
      "id": 1865402,
      "subaward_number": "52P402182-5",
      "description": "DIRECT EQUIPMENT RENTAL",
      "action_date": "2023-07-03",
      "amount": 242.97,
      "recipient_name": "UNITED RENTALS NORTH AMERICA INC"
    },
    {
      "id": 49662,
      "subaward_number": "52P402616-6",
      "description": "DIRECT SUBCONTRACT COSTS",
      "action_date": "2023-09-21",
      "amount": 2.0,
      "recipient_name": "DEFENSE MARITIME SOLUTIONS, INC."
    },
    {
      "id": 9567897,
      "subaward_number": "52P408624-9",
      "description": "DIRECT SUBCONTRACT COSTS",
      "action_date": "2025-02-10",
      "amount": -0.8,
      "recipient_name": "BOB TURNER'S CRANE SERVICE INCORPORATED"
    },
    {
      "id": 1871644,
      "subaward_number": "52P403326-5",
      "description": "DIRECT SUBCONTRACT COSTS",
      "action_date": "2023-01-31",
      "amount": -110.0,
      "recipient_name": "STANDARD INSPECTION SERVICES"
    },
    {
      "id": 1873331,
      "subaward_number": "52P403326-11",
      "description": "DIRECT SUBCONTRACT COSTS",
      "action_date": "2023-11-08",
      "amount": -410.0,
      "recipient_name": "STANDARD INSPECTION SERVICES"
    },
    {
      "id": 61669,
      "subaward_number": "52P402346-8",
      "description": "DIRECT SUBCONTRACT COSTS",
      "action_date": "2023-02-17",
      "amount": -533.0,
      "recipient_name": "SOUTH BAY SAND BLASTING AND TANK CLEANING, INC."
    },
    {
      "id": 1872480,
      "subaward_number": "52P404259-2",
      "description": "DIRECT SUBCONTRACT COSTS",
      "action_date": "2024-02-22",
      "amount": -1250.0,
      "recipient_name": "INSPEC TESTING, INC."
    },
    {
      "id": 1872164,
      "subaward_number": "52P403326-9",
      "description": "DIRECT SUBCONTRACT COSTS",
      "action_date": "2023-08-28",
      "amount": -1340.0,
      "recipient_name": "STANDARD INSPECTION SERVICES"
    },
    {
      "id": 52217,
      "subaward_number": "52P402933-50",
      "description": "DIRECT SUBCONTRACT COSTS",
      "action_date": "2024-03-06",
      "amount": -1452.0,
      "recipient_name": "PREMIER SCAFFOLD, INC."
    },
    {
      "id": 51954,
      "subaward_number": "52P402189-2",
      "description": "DIRECT SUBCONTRACT COSTS",
      "action_date": "2023-12-20",
      "amount": -3080.0,
      "recipient_name": "BREWER CRANE LLC"
    },
    {
      "id": 56541,
      "subaward_number": "52P403210-2",
      "description": "DIRECT SUBCONTRACT COSTS",
      "action_date": "2024-04-16",
      "amount": -3167.0,
      "recipient_name": "STANDARD CALIBRATIONS INC"
    },
    {
      "id": 1875021,
      "subaward_number": "52P402288-2",
      "description": "DIRECT SUBCONTRACT COSTS",
      "action_date": "2024-02-01",
      "amount": -4702.0,
      "recipient_name": "SAN DIEGO BAY PILOTS ASSOCIATION, INC"
    },
    {
      "id": 1874018,
      "subaward_number": "52P403095-32",
      "description": "DIRECT SUBCONTRACT COSTS",
      "action_date": "2024-02-01",
      "amount": -6511.0,
      "recipient_name": "SITTA, PAIGE & ASSOCIATES, INC."
    },
    {
      "id": 9619302,
      "subaward_number": "52P404259-4",
      "description": "DIRECT SUBCONTRACT COSTS",
      "action_date": "2025-03-12",
      "amount": -7150.0,
      "recipient_name": "INSPEC TESTING, INC."
    },
    {
      "id": 1871519,
      "subaward_number": "52P403095-15",
      "description": "DIRECT SUBCONTRACT COSTS",
      "action_date": "2023-06-22",
      "amount": -7829.0,
      "recipient_name": "SITTA, PAIGE & ASSOCIATES, INC."
    },
    {
      "id": 47834,
      "subaward_number": "52P402715-3",
      "description": "DIRECT SUBCONTRACT COSTS",
      "action_date": "2024-04-25",
      "amount": -10569.6,
      "recipient_name": "JAL ENTERPRISES, INC."
    },
    {
      "id": 61169,
      "subaward_number": "52P403210-1",
      "description": "DIRECT SUBCONTRACT COSTS",
      "action_date": "2024-03-19",
      "amount": -13764.0,
      "recipient_name": "STANDARD CALIBRATIONS INC"
    },
    {
      "id": 49094,
      "subaward_number": "52P402933-14",
      "description": "DIRECT SUBCONTRACT COSTS",
      "action_date": "2023-01-18",
      "amount": -15156.0,
      "recipient_name": "PREMIER SCAFFOLD, INC."
    },
    {
      "id": 62845,
      "subaward_number": "52P403248-9",
      "description": "DIRECT SUBCONTRACT COSTS",
      "action_date": "2023-01-17",
      "amount": -21242.0,
      "recipient_name": "L3HARRIS MARITIME SERVICES INC"
    },
    {
      "id": 59074,
      "subaward_number": "52P402346-46",
      "description": "DIRECT SUBCONTRACT COSTS",
      "action_date": "2024-05-30",
      "amount": -21576.1,
      "recipient_name": "SOUTH BAY SAND BLASTING AND TANK CLEANING, INC."
    },
    {
      "id": 1870165,
      "subaward_number": "52P408624-8",
      "description": "DIRECT SUBCONTRACT COSTS",
      "action_date": "2024-11-14",
      "amount": -23659.2,
      "recipient_name": "BOB TURNER'S CRANE SERVICE INCORPORATED"
    },
    {
      "id": 58972,
      "subaward_number": "52P402416-2",
      "description": "DIRECT SUBCONTRACT COSTS",
      "action_date": "2024-01-31",
      "amount": -30579.09,
      "recipient_name": "PACIFIC MARITIME GROUP INC"
    },
    {
      "id": 57099,
      "subaward_number": "52P402346-44",
      "description": "DIRECT SUBCONTRACT COSTS",
      "action_date": "2024-02-01",
      "amount": -46776.55,
      "recipient_name": "SOUTH BAY SAND BLASTING AND TANK CLEANING, INC."
    },
    {
      "id": 62128,
      "subaward_number": "52P402737-9",
      "description": "DIRECT SUBCONTRACT COSTS",
      "action_date": "2023-03-08",
      "amount": -47832.0,
      "recipient_name": "AMP UNITED LLC"
    },
    {
      "id": 1870622,
      "subaward_number": "52P402249-17",
      "description": "DIRECT SUBCONTRACT COSTS",
      "action_date": "2024-03-07",
      "amount": -70814.0,
      "recipient_name": "L3HARRIS MARITIME SERVICES INC"
    },
    {
      "id": 1865554,
      "subaward_number": "52P402958-3",
      "description": "DIRECT SUBCONTRACT COSTS",
      "action_date": "2023-01-03",
      "amount": -88054.0,
      "recipient_name": "JOHNSON CONTROLS FEDERAL SYSTEMS, LLC"
    },
    {
      "id": 59721,
      "subaward_number": "52P402416-3",
      "description": "DIRECT SUBCONTRACT COSTS",
      "action_date": "2024-02-27",
      "amount": -169284.15,
      "recipient_name": "PACIFIC MARITIME GROUP INC"
    },
    {
      "id": 9576916,
      "subaward_number": "52P402358-1",
      "description": "DIRECT SUBCONTRACT COSTS",
      "action_date": "2024-07-02",
      "amount": -295007.0,
      "recipient_name": "ROLLS-ROYCE MARINE NORTH AMERICA INC."
    },
    {
      "id": 9576906,
      "subaward_number": "52P403184-1",
      "description": "DIRECT SUBCONTRACT COSTS",
      "action_date": "2023-11-27",
      "amount": -313042.98,
      "recipient_name": "UNIVERSAL PROTECTION SERVICE, LIMITED PARTNERSHIP"
    }
  ]
}