{
  "award_id": "CONT_AWD_N0002423C2305_9700_-NONE-_-NONE-",
  "count": 60,
  "results": [
    {
      "id": "CONT_TX_9700_-NONE-_N0002423C2305_0_-NONE-_0",
      "type": "D",
      "type_description": "DEFINITIVE CONTRACT",
      "action_date": "2023-08-01",
      "action_type": null,
      "action_type_description": null,
      "modification_number": "0",
      "description": "CONSTRUCTION OF DDG 51 SHIPS FY23-27",
      "federal_action_obligation": 1593237569.0,
      "face_value_loan_guarantee": 0.0,
      "original_loan_subsidy_cost": 0.0
    },
    {
      "id": "CONT_TX_9700_-NONE-_N0002423C2305_P00001_-NONE-_0",
      "type": "D",
      "type_description": "DEFINITIVE CONTRACT",
      "action_date": "2023-08-07",
      "action_type": "C",
      "action_type_description": "FUNDING ONLY ACTION",
      "modification_number": "P00001",
      "description": "CONSTRUCTION OF DDG 51 SHIP",
      "federal_action_obligation": 169286000.0,
      "face_value_loan_guarantee": 0.0,
      "original_loan_subsidy_cost": 0.0
    },
    {
      "id": "CONT_TX_9700_-NONE-_N0002423C2305_P00002_-NONE-_0",
      "type": "D",
      "type_description": "DEFINITIVE CONTRACT",
      "action_date": "2023-08-15",
      "action_type": "C",
      "action_type_description": "FUNDING ONLY ACTION",
      "modification_number": "P00002",
      "description": "CONSTRUCTION OF DDG 51 SHIP",
      "federal_action_obligation": 0.0,
      "face_value_loan_guarantee": 0.0,
      "original_loan_subsidy_cost": 0.0
    },
    {
      "id": "CONT_TX_9700_-NONE-_N0002423C2305_P00003_-NONE-_0",
      "type": "D",
      "type_description": "DEFINITIVE CONTRACT",
      "action_date": "2023-12-19",
      "action_type": "M",
      "action_type_description": "OTHER ADMINISTRATIVE ACTION",
      "modification_number": "P00003",
      "description": "CONSTRUCTION OF DDG 51 SHIP",
      "federal_action_obligation": 0.0,
      "face_value_loan_guarantee": 0.0,
      "original_loan_subsidy_cost": 0.0
    },
    {
      "id": "CONT_TX_9700_-NONE-_N0002423C2305_P00004_-NONE-_0",
      "type": "D",
      "type_description": "DEFINITIVE CONTRACT",
      "action_date": "2024-02-14",
      "action_type": "M",
      "action_type_description": "OTHER ADMINISTRATIVE ACTION",
      "modification_number": "P00004",
      "description": "CONSTRUCTION OF DDG 51 SHIP",
      "federal_action_obligation": 0.0,
      "face_value_loan_guarantee": 0.0,
      "original_loan_subsidy_cost": 0.0
    },
    {
      "id": "CONT_TX_9700_-NONE-_N0002423C2305_P00005_-NONE-_0",
      "type": "D",
      "type_description": "DEFINITIVE CONTRACT",
      "action_date": "2024-03-01",
      "action_type": "M",
      "action_type_description": "OTHER ADMINISTRATIVE ACTION",
      "modification_number": "P00005",
      "description": "CONSTRUCTION OF DDG 51 SHIP",
      "federal_action_obligation": 23161000.0,
      "face_value_loan_guarantee": 0.0,
      "original_loan_subsidy_cost": 0.0
    },
    {
      "id": "CONT_TX_9700_-NONE-_N0002423C2305_P00006_-NONE-_0",
      "type": "D",
      "type_description": "DEFINITIVE CONTRACT",
      "action_date": "2024-05-21",
      "action_type": "G",
      "action_type_description": "EXERCISE AN OPTION",
      "modification_number": "P00006",
      "description": "CONSTRUCTION OF DDG 51 SHIP",
      "federal_action_obligation": 1496372021.0,
      "face_value_loan_guarantee": 0.0,
      "original_loan_subsidy_cost": 0.0
    },
    {
      "id": "CONT_TX_9700_-NONE-_N0002423C2305_A00001_-NONE-_0",
      "type": "D",
      "type_description": "DEFINITIVE CONTRACT",
      "action_date": "2024-07-16",
      "action_type": "B",
      "action_type_description": "SUPPLEMENTAL AGREEMENT FOR WORK WITHIN SCOPE",
      "modification_number": "A00001",
      "description": "FMR 12108MNO",
      "federal_action_obligation": 123045.0,
      "face_value_loan_guarantee": 0.0,
      "original_loan_subsidy_cost": 0.0
    },
    {
      "id": "CONT_TX_9700_-NONE-_N0002423C2305_P00007_-NONE-_0",
      "type": "D",
      "type_description": "DEFINITIVE CONTRACT",
      "action_date": "2024-07-30",
      "action_type": "M",
      "action_type_description": "OTHER ADMINISTRATIVE ACTION",
      "modification_number": "P00007",
      "description": "CONSTRUCTION OF DDG 51 SHIP",
      "federal_action_obligation": 0.0,
      "face_value_loan_guarantee": 0.0,
      "original_loan_subsidy_cost": 0.0
    },
    {
      "id": "CONT_TX_9700_-NONE-_N0002423C2305_A00002_-NONE-_0",
      "type": "D",
      "type_description": "DEFINITIVE CONTRACT",
      "action_date": "2024-08-28",
      "action_type": "B",
      "action_type_description": "SUPPLEMENTAL AGREEMENT FOR WORK WITHIN SCOPE",
      "modification_number": "A00002",
      "description": "51-2051 (HMR-00792)",
      "federal_action_obligation": 0.0,
      "face_value_loan_guarantee": 0.0,
      "original_loan_subsidy_cost": 0.0
    },
    {
      "id": "CONT_TX_9700_-NONE-_N0002423C2305_A00003_-NONE-_0",
      "type": "D",
      "type_description": "DEFINITIVE CONTRACT",
      "action_date": "2024-09-13",
      "action_type": "M",
      "action_type_description": "OTHER ADMINISTRATIVE ACTION",
      "modification_number": "A00003",
      "description": "THIS MODIFICATION ESTABLISHED CY23 ECONOMIC PRICE ADJUSTMENT FOR CLINS 2300 (DDG 140), 2400 (DDG 144) AND 2600 (DDG 148)",
      "federal_action_obligation": 0.0,
      "face_value_loan_guarantee": 0.0,
      "original_loan_subsidy_cost": 0.0
    },
    {
      "id": "CONT_TX_9700_-NONE-_N0002423C2305_A00004_-NONE-_0",
      "type": "D",
      "type_description": "DEFINITIVE CONTRACT",
      "action_date": "2024-10-02",
      "action_type": "B",
      "action_type_description": "SUPPLEMENTAL AGREEMENT FOR WORK WITHIN SCOPE",
      "modification_number": "A00004",
      "description": "51-2060 (HMR 00803), DB-3712C1 (FMR 12124MNO), WF-3714 (FMR-12132NO), WF-3711 (FMR-12116MNO), WF-3705 (FMR-12083NO), DB-3713 (FMR 12131NO), WF-3707 (FMR-12105NO), WF-3708 (FMR 12110NO)",
      "federal_action_obligation": 57724.0,
      "face_value_loan_guarantee": 0.0,
      "original_loan_subsidy_cost": 0.0
    },
    {
      "id": "CONT_TX_9700_-NONE-_N0002423C2305_A00005_-NONE-_0",
      "type": "D",
      "type_description": "DEFINITIVE CONTRACT",
      "action_date": "2024-10-15",
      "action_type": "B",
      "action_type_description": "SUPPLEMENTAL AGREEMENT FOR WORK WITHIN SCOPE",
      "modification_number": "A00005",
      "description": "CONSTRUCTION OF DDG 51 SHIP",
      "federal_action_obligation": 106143.0,
      "face_value_loan_guarantee": 0.0,
      "original_loan_subsidy_cost": 0.0
    },
    {
      "id": "CONT_TX_9700_-NONE-_N0002423C2305_A00006_-NONE-_0",
      "type": "D",
      "type_description": "DEFINITIVE CONTRACT",
      "action_date": "2024-10-23",
      "action_type": "B",
      "action_type_description": "SUPPLEMENTAL AGREEMENT FOR WORK WITHIN SCOPE",
      "modification_number": "A00006",
      "description": "CONSTRUCTION OF DDG 51 SHIP",
      "federal_action_obligation": 80669.0,
      "face_value_loan_guarantee": 0.0,
      "original_loan_subsidy_cost": 0.0
    },
    {
      "id": "CONT_TX_9700_-NONE-_N0002423C2305_A00007_-NONE-_0",
      "type": "D",
      "type_description": "DEFINITIVE CONTRACT",
      "action_date": "2024-11-07",
      "action_type": "B",
      "action_type_description": "SUPPLEMENTAL AGREEMENT FOR WORK WITHIN SCOPE",
      "modification_number": "A00007",
      "description": "51-2064 (HMR-00802), FMR 12109MNO, DB-3692 (FMR-8170MNO), DB-3676 (FMR-8168MNO), DB-3698C1 (FMR-12085NO)",
      "federal_action_obligation": 108414.0,
      "face_value_loan_guarantee": 0.0,
      "original_loan_subsidy_cost": 0.0
    },
    {
      "id": "CONT_TX_9700_-NONE-_N0002423C2305_A00008_-NONE-_0",
      "type": "D",
      "type_description": "DEFINITIVE CONTRACT",
      "action_date": "2024-11-22",
      "action_type": "B",
      "action_type_description": "SUPPLEMENTAL AGREEMENT FOR WORK WITHIN SCOPE",
      "modification_number": "A00008",
      "description": "DB-3702C1 (FMR-12112MNO), 51-2062 (HMR-00801)",
      "federal_action_obligation": 587792.0,
      "face_value_loan_guarantee": 0.0,
      "original_loan_subsidy_cost": 0.0
    },
    {
      "id": "CONT_TX_9700_-NONE-_N0002423C2305_P00008_-NONE-_0",
      "type": "D",
      "type_description": "DEFINITIVE CONTRACT",
      "action_date": "2024-12-04",
      "action_type": "C",
      "action_type_description": "FUNDING ONLY ACTION",
      "modification_number": "P00008",
      "description": "CONSTRUCTION OF DDG 51 SHIP",
      "federal_action_obligation": 59342000.0,
      "face_value_loan_guarantee": 0.0,
      "original_loan_subsidy_cost": 0.0
    },
    {
      "id": "CONT_TX_9700_-NONE-_N0002423C2305_A00009_-NONE-_0",
      "type": "D",
      "type_description": "DEFINITIVE CONTRACT",
      "action_date": "2024-12-09",
      "action_type": "B",
      "action_type_description": "SUPPLEMENTAL AGREEMENT FOR WORK WITHIN SCOPE",
      "modification_number": "A00009",
      "description": "WF-3692 (FMR 12148O), 51-2065 (HMR 00806), FMR-12136MNO",
      "federal_action_obligation": 152560.0,
      "face_value_loan_guarantee": 0.0,
      "original_loan_subsidy_cost": 0.0
    },
    {
      "id": "CONT_TX_9700_-NONE-_N0002423C2305_P00009_-NONE-_0",
      "type": "D",
      "type_description": "DEFINITIVE CONTRACT",
      "action_date": "2024-12-09",
      "action_type": "M",
      "action_type_description": "OTHER ADMINISTRATIVE ACTION",
      "modification_number": "P00009",
      "description": "CONSTRUCTION OF DDG 51 SHIP",
      "federal_action_obligation": 0.0,
      "face_value_loan_guarantee": 0.0,
      "original_loan_subsidy_cost": 0.0
    },
    {
      "id": "CONT_TX_9700_-NONE-_N0002423C2305_P00010_-NONE-_0",
      "type": "D",
      "type_description": "DEFINITIVE CONTRACT",
      "action_date": "2024-12-13",
      "action_type": "C",
      "action_type_description": "FUNDING ONLY ACTION",
      "modification_number": "P00010",
      "description": "CONSTRUCTION OF DDG 51 SHIP",
      "federal_action_obligation": 21509000.0,
      "face_value_loan_guarantee": 0.0,
      "original_loan_subsidy_cost": 0.0
    },
    {
      "id": "CONT_TX_9700_-NONE-_N0002423C2305_A00010_-NONE-_0",
      "type": "D",
      "type_description": "DEFINITIVE CONTRACT",
      "action_date": "2024-12-18",
      "action_type": "B",
      "action_type_description": "SUPPLEMENTAL AGREEMENT FOR WORK WITHIN SCOPE",
      "modification_number": "A00010",
      "description": "FMR-12142MNO",
      "federal_action_obligation": 23872.0,
      "face_value_loan_guarantee": 0.0,
      "original_loan_subsidy_cost": 0.0
    },
    {
      "id": "CONT_TX_9700_-NONE-_N0002423C2305_A00011_-NONE-_0",
      "type": "D",
      "type_description": "DEFINITIVE CONTRACT",
      "action_date": "2025-01-31",
      "action_type": "B",
      "action_type_description": "SUPPLEMENTAL AGREEMENT FOR WORK WITHIN SCOPE",
      "modification_number": "A00011",
      "description": "51-2059C1",
      "federal_action_obligation": 2737459.0,
      "face_value_loan_guarantee": 0.0,
      "original_loan_subsidy_cost": 0.0
    },
    {
      "id": "CONT_TX_9700_-NONE-_N0002423C2305_A00012_-NONE-_0",
      "type": "D",
      "type_description": "DEFINITIVE CONTRACT",
      "action_date": "2025-02-10",
      "action_type": "B",
      "action_type_description": "SUPPLEMENTAL AGREEMENT FOR WORK WITHIN SCOPE",
      "modification_number": "A00012",
      "description": "CONSTRUCTION OF DDG 51 SHIP",
      "federal_action_obligation": 2214.0,
      "face_value_loan_guarantee": 0.0,
      "original_loan_subsidy_cost": 0.0
    },
    {
      "id": "CONT_TX_9700_-NONE-_N0002423C2305_AZ0001_-NONE-_0",
      "type": "D",
      "type_description": "DEFINITIVE CONTRACT",
      "action_date": "2025-02-27",
      "action_type": "B",
      "action_type_description": "SUPPLEMENTAL AGREEMENT FOR WORK WITHIN SCOPE",
      "modification_number": "AZ0001",
      "description": "FMR-12108MNO, DB-3706 (FMR-8171MNO), WF-3701R1 (FMR-12162NO), 51-2067 (HMR-00807), WF-3721 (FMR 12163MNO)",
      "federal_action_obligation": 393751.0,
      "face_value_loan_guarantee": 0.0,
      "original_loan_subsidy_cost": 0.0
    },
    {
      "id": "CONT_TX_9700_-NONE-_N0002423C2305_A00013_-NONE-_0",
      "type": "D",
      "type_description": "DEFINITIVE CONTRACT",
      "action_date": "2025-03-13",
      "action_type": "B",
      "action_type_description": "SUPPLEMENTAL AGREEMENT FOR WORK WITHIN SCOPE",
      "modification_number": "A00013",
      "description": "FMR 12166NO",
      "federal_action_obligation": 2613.0,
      "face_value_loan_guarantee": 0.0,
      "original_loan_subsidy_cost": 0.0
    },
    {
      "id": "CONT_TX_9700_-NONE-_N0002423C2305_A00014_-NONE-_0",
      "type": "D",
      "type_description": "DEFINITIVE CONTRACT",
      "action_date": "2025-04-11",
      "action_type": "B",
      "action_type_description": "SUPPLEMENTAL AGREEMENT FOR WORK WITHIN SCOPE",
      "modification_number": "A00014",
      "description": "FMR 12165NO",
      "federal_action_obligation": 24068.0,
      "face_value_loan_guarantee": 0.0,
      "original_loan_subsidy_cost": 0.0
    },
    {
      "id": "CONT_TX_9700_-NONE-_N0002423C2305_A00015_-NONE-_0",
      "type": "D",
      "type_description": "DEFINITIVE CONTRACT",
      "action_date": "2025-04-24",
      "action_type": "B",
      "action_type_description": "SUPPLEMENTAL AGREEMENT FOR WORK WITHIN SCOPE",
      "modification_number": "A00015",
      "description": "CONSTRUCTION OF DDG 51 SHIP",
      "federal_action_obligation": 210963.0,
      "face_value_loan_guarantee": 0.0,
      "original_loan_subsidy_cost": 0.0
    },
    {
      "id": "CONT_TX_9700_-NONE-_N0002423C2305_A00016_-NONE-_0",
      "type": "D",
      "type_description": "DEFINITIVE CONTRACT",
      "action_date": "2025-04-28",
      "action_type": "D",
      "action_type_description": "CHANGE ORDER",
      "modification_number": "A00016",
      "description": "SHORE BASED SPARE 138-FA01",
      "federal_action_obligation": 6044572.0,
      "face_value_loan_guarantee": 0.0,
      "original_loan_subsidy_cost": 0.0
    },
    {
      "id": "CONT_TX_9700_-NONE-_N0002423C2305_A00017_-NONE-_0",
      "type": "D",
      "type_description": "DEFINITIVE CONTRACT",
      "action_date": "2025-05-02",
      "action_type": "B",
      "action_type_description": "SUPPLEMENTAL AGREEMENT FOR WORK WITHIN SCOPE",
      "modification_number": "A00017",
      "description": "51-2072(HMR-00812), DB-3729C1(FMR-12176NO), 51-2071C1(HMR-00811)",
      "federal_action_obligation": 1404047.0,
      "face_value_loan_guarantee": 0.0,
      "original_loan_subsidy_cost": 0.0
    },
    {
      "id": "CONT_TX_9700_-NONE-_N0002423C2305_P00011_-NONE-_0",
      "type": "D",
      "type_description": "DEFINITIVE CONTRACT",
      "action_date": "2025-05-16",
      "action_type": "C",
      "action_type_description": "FUNDING ONLY ACTION",
      "modification_number": "P00011",
      "description": "CONSTRUCTION OF DDG 51 SHIP",
      "federal_action_obligation": 121515396.0,
      "face_value_loan_guarantee": 0.0,
      "original_loan_subsidy_cost": 0.0
    },
    {
      "id": "CONT_TX_9700_-NONE-_N0002423C2305_A00018_-NONE-_0",
      "type": "D",
      "type_description": "DEFINITIVE CONTRACT",
      "action_date": "2025-05-27",
      "action_type": "B",
      "action_type_description": "SUPPLEMENTAL AGREEMENT FOR WORK WITHIN SCOPE",
      "modification_number": "A00018",
      "description": "WF-3731R1(FMR 12177NO), WF-3728C1(FMR 12180NO)",
      "federal_action_obligation": 27341.0,
      "face_value_loan_guarantee": 0.0,
      "original_loan_subsidy_cost": 0.0
    },
    {
      "id": "CONT_TX_9700_-NONE-_N0002423C2305_A00019_-NONE-_0",
      "type": "D",
      "type_description": "DEFINITIVE CONTRACT",
      "action_date": "2025-06-06",
      "action_type": "B",
      "action_type_description": "SUPPLEMENTAL AGREEMENT FOR WORK WITHIN SCOPE",
      "modification_number": "A00019",
      "description": "CONSTRUCTION OF DDG 51 SHIP",
      "federal_action_obligation": 2045961.0,
      "face_value_loan_guarantee": 0.0,
      "original_loan_subsidy_cost": 0.0
    },
    {
      "id": "CONT_TX_9700_-NONE-_N0002423C2305_A00020_-NONE-_0",
      "type": "D",
      "type_description": "DEFINITIVE CONTRACT",
      "action_date": "2025-06-17",
      "action_type": "B",
      "action_type_description": "SUPPLEMENTAL AGREEMENT FOR WORK WITHIN SCOPE",
      "modification_number": "A00020",
      "description": "ECP 51-2057R3, HMR 00805",
      "federal_action_obligation": 291213.0,
      "face_value_loan_guarantee": 0.0,
      "original_loan_subsidy_cost": 0.0
    },
    {
      "id": "CONT_TX_9700_-NONE-_N0002423C2305_A00021_-NONE-_0",
      "type": "D",
      "type_description": "DEFINITIVE CONTRACT",
      "action_date": "2025-06-18",
      "action_type": "B",
      "action_type_description": "SUPPLEMENTAL AGREEMENT FOR WORK WITHIN SCOPE",
      "modification_number": "A00021",
      "description": "DB-3725C1 AND FMR 12183MNO",
      "federal_action_obligation": 115722.0,
      "face_value_loan_guarantee": 0.0,
      "original_loan_subsidy_cost": 0.0
    },
    {
      "id": "CONT_TX_9700_-NONE-_N0002423C2305_A00022_-NONE-_0",
      "type": "D",
      "type_description": "DEFINITIVE CONTRACT",
      "action_date": "2025-06-23",
      "action_type": "M",
      "action_type_description": "OTHER ADMINISTRATIVE ACTION",
      "modification_number": "A00022",
      "description": "CY24 EPA",
      "federal_action_obligation": 0.0,
      "face_value_loan_guarantee": 0.0,
      "original_loan_subsidy_cost": 0.0
    },
    {
      "id": "CONT_TX_9700_-NONE-_N0002423C2305_A00023_-NONE-_0",
      "type": "D",
      "type_description": "DEFINITIVE CONTRACT",
      "action_date": "2025-06-25",
      "action_type": "B",
      "action_type_description": "SUPPLEMENTAL AGREEMENT FOR WORK WITHIN SCOPE",
      "modification_number": "A00023",
      "description": "FMR 12189MNO & FMR 12182MNO",
      "federal_action_obligation": 115510.0,
      "face_value_loan_guarantee": 0.0,
      "original_loan_subsidy_cost": 0.0
    },
    {
      "id": "CONT_TX_9700_-NONE-_N0002423C2305_P00012_-NONE-_0",
      "type": "D",
      "type_description": "DEFINITIVE CONTRACT",
      "action_date": "2025-07-15",
      "action_type": "M",
      "action_type_description": "OTHER ADMINISTRATIVE ACTION",
      "modification_number": "P00012",
      "description": "CONSTRUCTION OF DDG 51 SHIP",
      "federal_action_obligation": 5257484.0,
      "face_value_loan_guarantee": 0.0,
      "original_loan_subsidy_cost": 0.0
    },
    {
      "id": "CONT_TX_9700_-NONE-_N0002423C2305_P00013_-NONE-_0",
      "type": "D",
      "type_description": "DEFINITIVE CONTRACT",
      "action_date": "2025-07-31",
      "action_type": "G",
      "action_type_description": "EXERCISE AN OPTION",
      "modification_number": "P00013",
      "description": "CONSTRUCTION OF DDG 51 SHIP",
      "federal_action_obligation": 1519369714.0,
      "face_value_loan_guarantee": 0.0,
      "original_loan_subsidy_cost": 0.0
    },
    {
      "id": "CONT_TX_9700_-NONE-_N0002423C2305_P00014_-NONE-_0",
      "type": "D",
      "type_description": "DEFINITIVE CONTRACT",
      "action_date": "2025-08-04",
      "action_type": "M",
      "action_type_description": "OTHER ADMINISTRATIVE ACTION",
      "modification_number": "P00014",
      "description": "CONSTRUCTION OF DDG 51 SHIP",
      "federal_action_obligation": 0.0,
      "face_value_loan_guarantee": 0.0,
      "original_loan_subsidy_cost": 0.0
    },
    {
      "id": "CONT_TX_9700_-NONE-_N0002423C2305_A00024_-NONE-_0",
      "type": "D",
      "type_description": "DEFINITIVE CONTRACT",
      "action_date": "2025-08-08",
      "action_type": "B",
      "action_type_description": "SUPPLEMENTAL AGREEMENT FOR WORK WITHIN SCOPE",
      "modification_number": "A00024",
      "description": "WF-3737 (FMR-12187MNO) & DB-37341.",
      "federal_action_obligation": 51489.0,
      "face_value_loan_guarantee": 0.0,
      "original_loan_subsidy_cost": 0.0
    },
    {
      "id": "CONT_TX_9700_-NONE-_N0002423C2305_A00025_-NONE-_0",
      "type": "D",
      "type_description": "DEFINITIVE CONTRACT",
      "action_date": "2025-08-15",
      "action_type": "B",
      "action_type_description": "SUPPLEMENTAL AGREEMENT FOR WORK WITHIN SCOPE",
      "modification_number": "A00025",
      "description": "CONSTRUCTION OF DDG 51 SHIP",
      "federal_action_obligation": 7236.0,
      "face_value_loan_guarantee": 0.0,
      "original_loan_subsidy_cost": 0.0
    },
    {
      "id": "CONT_TX_9700_-NONE-_N0002423C2305_A00026_-NONE-_0",
      "type": "D",
      "type_description": "DEFINITIVE CONTRACT",
      "action_date": "2025-08-20",
      "action_type": "B",
      "action_type_description": "SUPPLEMENTAL AGREEMENT FOR WORK WITHIN SCOPE",
      "modification_number": "A00026",
      "description": "WF-3742R1, WF-3744",
      "federal_action_obligation": 10670.0,
      "face_value_loan_guarantee": 0.0,
      "original_loan_subsidy_cost": 0.0
    },
    {
      "id": "CONT_TX_9700_-NONE-_N0002423C2305_P00015_-NONE-_0",
      "type": "D",
      "type_description": "DEFINITIVE CONTRACT",
      "action_date": "2025-08-26",
      "action_type": "M",
      "action_type_description": "OTHER ADMINISTRATIVE ACTION",
      "modification_number": "P00015",
      "description": "CONSTRUCTION OF DDG 51 SHIP",
      "federal_action_obligation": 0.0,
      "face_value_loan_guarantee": 0.0,
      "original_loan_subsidy_cost": 0.0
    },
    {
      "id": "CONT_TX_9700_-NONE-_N0002423C2305_A00027_-NONE-_0",
      "type": "D",
      "type_description": "DEFINITIVE CONTRACT",
      "action_date": "2025-08-29",
      "action_type": "B",
      "action_type_description": "SUPPLEMENTAL AGREEMENT FOR WORK WITHIN SCOPE",
      "modification_number": "A00027",
      "description": "WF-3741 (FMR-12206NO)",
      "federal_action_obligation": 11228.0,
      "face_value_loan_guarantee": 0.0,
      "original_loan_subsidy_cost": 0.0
    },
    {
      "id": "CONT_TX_9700_-NONE-_N0002423C2305_P00016_-NONE-_0",
      "type": "D",
      "type_description": "DEFINITIVE CONTRACT",
      "action_date": "2025-09-04",
      "action_type": "M",
      "action_type_description": "OTHER ADMINISTRATIVE ACTION",
      "modification_number": "P00016",
      "description": "CONSTRUCTION OF DDG 51 SHIP",
      "federal_action_obligation": 0.0,
      "face_value_loan_guarantee": 0.0,
      "original_loan_subsidy_cost": 0.0
    },
    {
      "id": "CONT_TX_9700_-NONE-_N0002423C2305_A00028_-NONE-_0",
      "type": "D",
      "type_description": "DEFINITIVE CONTRACT",
      "action_date": "2025-09-05",
      "action_type": "B",
      "action_type_description": "SUPPLEMENTAL AGREEMENT FOR WORK WITHIN SCOPE",
      "modification_number": "A00028",
      "description": "FMR 12122MNO AND HMR 00815",
      "federal_action_obligation": 53871.0,
      "face_value_loan_guarantee": 0.0,
      "original_loan_subsidy_cost": 0.0
    },
    {
      "id": "CONT_TX_9700_-NONE-_N0002423C2305_AZ0002_-NONE-_0",
      "type": "D",
      "type_description": "DEFINITIVE CONTRACT",
      "action_date": "2025-09-18",
      "action_type": "B",
      "action_type_description": "SUPPLEMENTAL AGREEMENT FOR WORK WITHIN SCOPE",
      "modification_number": "AZ0002",
      "description": "WF-3747 (FMR-12213NO), FMR-12136MNO DEFIN",
      "federal_action_obligation": 746.0,
      "face_value_loan_guarantee": 0.0,
      "original_loan_subsidy_cost": 0.0
    },
    {
      "id": "CONT_TX_9700_-NONE-_N0002423C2305_A00029_-NONE-_0",
      "type": "D",
      "type_description": "DEFINITIVE CONTRACT",
      "action_date": "2025-09-25",
      "action_type": "B",
      "action_type_description": "SUPPLEMENTAL AGREEMENT FOR WORK WITHIN SCOPE",
      "modification_number": "A00029",
      "description": "CONSTRUCTION OF DDG 51 SHIP WF-3748 AND WF-3746",
      "federal_action_obligation": 69373.0,
      "face_value_loan_guarantee": 0.0,
      "original_loan_subsidy_cost": 0.0
    },
    {
      "id": "CONT_TX_9700_-NONE-_N0002423C2305_P00017_-NONE-_0",
      "type": "D",
      "type_description": "DEFINITIVE CONTRACT",
      "action_date": "2025-10-15",
      "action_type": "M",
      "action_type_description": "OTHER ADMINISTRATIVE ACTION",
      "modification_number": "P00017",
      "description": "CONSTRUCTION OF DDG 51 SHIP",
      "federal_action_obligation": 0.0,
      "face_value_loan_guarantee": 0.0,
      "original_loan_subsidy_cost": 0.0
    },
    {
      "id": "CONT_TX_9700_-NONE-_N0002423C2305_A00030_-NONE-_0",
      "type": "D",
      "type_description": "DEFINITIVE CONTRACT",
      "action_date": "2025-10-22",
      "action_type": "B",
      "action_type_description": "SUPPLEMENTAL AGREEMENT FOR WORK WITHIN SCOPE",
      "modification_number": "A00030",
      "description": "FMR-12094MNO, FMR-12107MNO, FMR-12150MNO, FMR-12160MNO, FMR-12178MNO",
      "federal_action_obligation": 1699706.0,
      "face_value_loan_guarantee": 0.0,
      "original_loan_subsidy_cost": 0.0
    },
    {
      "id": "CONT_TX_9700_-NONE-_N0002423C2305_A00031_-NONE-_0",
      "type": "D",
      "type_description": "DEFINITIVE CONTRACT",
      "action_date": "2025-11-04",
      "action_type": "B",
      "action_type_description": "SUPPLEMENTAL AGREEMENT FOR WORK WITHIN SCOPE",
      "modification_number": "A00031",
      "description": "CONSTRUCTION OF DDG 51 SHIP",
      "federal_action_obligation": -11799.0,
      "face_value_loan_guarantee": 0.0,
      "original_loan_subsidy_cost": 0.0
    },
    {
      "id": "CONT_TX_9700_-NONE-_N0002423C2305_A00032_-NONE-_0",
      "type": "D",
      "type_description": "DEFINITIVE CONTRACT",
      "action_date": "2025-12-01",
      "action_type": "B",
      "action_type_description": "SUPPLEMENTAL AGREEMENT FOR WORK WITHIN SCOPE",
      "modification_number": "A00032",
      "description": "FMR-12178MNO",
      "federal_action_obligation": 102697.0,
      "face_value_loan_guarantee": 0.0,
      "original_loan_subsidy_cost": 0.0
    },
    {
      "id": "CONT_TX_9700_-NONE-_N0002423C2305_A00033_-NONE-_0",
      "type": "D",
      "type_description": "DEFINITIVE CONTRACT",
      "action_date": "2025-12-11",
      "action_type": "B",
      "action_type_description": "SUPPLEMENTAL AGREEMENT FOR WORK WITHIN SCOPE",
      "modification_number": "A00033",
      "description": "51-2066R1C1",
      "federal_action_obligation": 1504372.0,
      "face_value_loan_guarantee": 0.0,
      "original_loan_subsidy_cost": 0.0
    },
    {
      "id": "CONT_TX_9700_-NONE-_N0002423C2305_A00034_-NONE-_0",
      "type": "D",
      "type_description": "DEFINITIVE CONTRACT",
      "action_date": "2025-12-15",
      "action_type": "B",
      "action_type_description": "SUPPLEMENTAL AGREEMENT FOR WORK WITHIN SCOPE",
      "modification_number": "A00034",
      "description": "FMR-12230MNO, FMR-12198MNO",
      "federal_action_obligation": 28658.0,
      "face_value_loan_guarantee": 0.0,
      "original_loan_subsidy_cost": 0.0
    },
    {
      "id": "CONT_TX_9700_-NONE-_N0002423C2305_P00018_-NONE-_0",
      "type": "D",
      "type_description": "DEFINITIVE CONTRACT",
      "action_date": "2025-12-19",
      "action_type": "M",
      "action_type_description": "OTHER ADMINISTRATIVE ACTION",
      "modification_number": "P00018",
      "description": "CONSTRUCTION OF DDG 51 SHIP",
      "federal_action_obligation": 0.0,
      "face_value_loan_guarantee": 0.0,
      "original_loan_subsidy_cost": 0.0
    },
    {
      "id": "CONT_TX_9700_-NONE-_N0002423C2305_A00035_-NONE-_0",
      "type": "D",
      "type_description": "DEFINITIVE CONTRACT",
      "action_date": "2025-12-23",
      "action_type": "B",
      "action_type_description": "SUPPLEMENTAL AGREEMENT FOR WORK WITHIN SCOPE",
      "modification_number": "A00035",
      "description": "FMR 12229MNO",
      "federal_action_obligation": 92060.0,
      "face_value_loan_guarantee": 0.0,
      "original_loan_subsidy_cost": 0.0
    },
    {
      "id": "CONT_TX_9700_-NONE-_N0002423C2305_A00036_-NONE-_0",
      "type": "D",
      "type_description": "DEFINITIVE CONTRACT",
      "action_date": "2026-01-30",
      "action_type": "B",
      "action_type_description": "SUPPLEMENTAL AGREEMENT FOR WORK WITHIN SCOPE",
      "modification_number": "A00036",
      "description": "FABRICATE ARRAY COVERS",
      "federal_action_obligation": 247849.0,
      "face_value_loan_guarantee": 0.0,
      "original_loan_subsidy_cost": 0.0
    },
    {
      "id": "CONT_TX_9700_-NONE-_N0002423C2305_AZ0003_-NONE-_0",
      "type": "D",
      "type_description": "DEFINITIVE CONTRACT",
      "action_date": "2026-02-10",
      "action_type": "B",
      "action_type_description": "SUPPLEMENTAL AGREEMENT FOR WORK WITHIN SCOPE",
      "modification_number": "AZ0003",
      "description": "CONSTRUCTION OF DDG 51 SHIP",
      "federal_action_obligation": -63193.0,
      "face_value_loan_guarantee": 0.0,
      "original_loan_subsidy_cost": 0.0
    },
    {
      "id": "CONT_TX_9700_-NONE-_N0002423C2305_P00019_-NONE-_0",
      "type": "D",
      "type_description": "DEFINITIVE CONTRACT",
      "action_date": "2026-03-10",
      "action_type": "M",
      "action_type_description": "OTHER ADMINISTRATIVE ACTION",
      "modification_number": "P00019",
      "description": "CONSTRUCTION OF DDG 51 SHIP",
      "federal_action_obligation": 70000.0,
      "face_value_loan_guarantee": 0.0,
      "original_loan_subsidy_cost": 0.0
    },
    {
      "id": "CONT_TX_9700_-NONE-_N0002423C2305_P00020_-NONE-_0",
      "type": "D",
      "type_description": "DEFINITIVE CONTRACT",
      "action_date": "2026-03-20",
      "action_type": "M",
      "action_type_description": "OTHER ADMINISTRATIVE ACTION",
      "modification_number": "P00020",
      "description": "CONSTRUCTION OF DDG 51 SHIP",
      "federal_action_obligation": 0.0,
      "face_value_loan_guarantee": 0.0,
      "original_loan_subsidy_cost": 0.0
    }
  ]
}