{
  "award_id": "CONT_AWD_W912EP19F0058_9700_W912EP17A0010_9700",
  "count": 2,
  "results": [
    {
      "id": "CONT_TX_9700_9700_W912EP19F0058_0_W912EP17A0010_0",
      "type": "A",
      "type_description": "BPA CALL",
      "action_date": "2019-01-30",
      "action_type": null,
      "action_type_description": null,
      "modification_number": "0",
      "description": "IGF::CL::IGF SV JACKSONVILLE PROPELLER REPAIR",
      "federal_action_obligation": 18262.1,
      "face_value_loan_guarantee": 0.0,
      "original_loan_subsidy_cost": 0.0
    },
    {
      "id": "CONT_TX_9700_9700_W912EP19F0058_P00001_W912EP17A0010_0",
      "type": "A",
      "type_description": "BPA CALL",
      "action_date": "2020-01-13",
      "action_type": "M",
      "action_type_description": "OTHER ADMINISTRATIVE ACTION",
      "modification_number": "P00001",
      "description": "FUNDING DEOB SV JACKSONVILLE PROPELLER REPAIR",
      "federal_action_obligation": -4708.1,
      "face_value_loan_guarantee": 0.0,
      "original_loan_subsidy_cost": 0.0
    }
  ]
}