{
  "award_id": "CONT_IDV_FA527022A0017_9700",
  "count": 3,
  "results": [
    {
      "id": "CONT_TX_9700_-NONE-_FA527022A0017_0_-NONE-_-NONE-",
      "type": "IDV_E",
      "type_description": "BPA",
      "action_date": "2022-05-23",
      "action_type": null,
      "action_type_description": null,
      "modification_number": "0",
      "description": "TO PERFORM PUMP OUT AND CLEANING SERVICES OF BILGES AND OIL/WATER SEPARATORS ON U. S. ARMY LANDING CRAFT UTILITIES (LCUS) AT THE FOLLOWING U.S MILLITARY INSTALLATIONS IN OKINAWA, JAPAN: NOT TO LIMIT NAHA MILITARY PORT AND WHITE BEACH, OKINAWA, JAPAN.",
      "federal_action_obligation": 0.0,
      "face_value_loan_guarantee": 0.0,
      "original_loan_subsidy_cost": 0.0
    },
    {
      "id": "CONT_TX_9700_-NONE-_FA527022A0017_P00001_-NONE-_-NONE-",
      "type": "IDV_E",
      "type_description": "BPA",
      "action_date": "2022-08-02",
      "action_type": "M",
      "action_type_description": "OTHER ADMINISTRATIVE ACTION",
      "modification_number": "P00001",
      "description": "THE CONTRACTOR SHALL PROVIDE LABOR/MANPOWER AND APPROPRIATE LICENSE/QUALIFICATION NECESSARY TO PERFORM PUMP OUT AND CLEANING SERVICES OF BILGES AND OIL/WATER SEPARATORS ON U. S. ARMY LANDING CRAFT UTILITIES (LCUS)",
      "federal_action_obligation": 0.0,
      "face_value_loan_guarantee": 0.0,
      "original_loan_subsidy_cost": 0.0
    },
    {
      "id": "CONT_TX_9700_-NONE-_FA527022A0017_P00002_-NONE-_-NONE-",
      "type": "IDV_E",
      "type_description": "BPA",
      "action_date": "2022-12-06",
      "action_type": "D",
      "action_type_description": "CHANGE ORDER",
      "modification_number": "P00002",
      "description": "UPDATE PWS AND PRICE LIST MODIFICATION",
      "federal_action_obligation": 0.0,
      "face_value_loan_guarantee": 0.0,
      "original_loan_subsidy_cost": 0.0
    }
  ]
}